{
"meta":{"test_sets":[],"test_metrics":[],"learn_metrics":[{"best_value":"Min","name":"RMSE"}],"launch_mode":"Train","parameters":"","iteration_count":1000,"learn_sets":["learn"],"name":"experiment"},
"iterations":[
{"learn":[8749.730806],"iteration":0,"passed_time":0.260429211,"remaining_time":260.1687818},
{"learn":[8569.249983],"iteration":1,"passed_time":0.3493327212,"remaining_time":174.3170279},
{"learn":[8406.607282],"iteration":2,"passed_time":0.4012354913,"remaining_time":133.3439283},
{"learn":[8258.672336],"iteration":3,"passed_time":0.4883707611,"remaining_time":121.6043195},
{"learn":[8115.590582],"iteration":4,"passed_time":0.5481313971,"remaining_time":109.078148},
{"learn":[7972.497219],"iteration":5,"passed_time":0.6322509632,"remaining_time":104.7429096},
{"learn":[7829.599703],"iteration":6,"passed_time":0.6980365189,"remaining_time":99.02146618},
{"learn":[7663.237364],"iteration":7,"passed_time":0.7674492587,"remaining_time":95.16370808},
{"learn":[7515.10622],"iteration":8,"passed_time":0.8437252692,"remaining_time":92.90352686},,
{"learn":[7449.576399],"iteration":9,"passed_time":0.8850117546,"remaining_time":87.61616371,,
{"learn":[7305.789543],"iteration":10,"passed_time":0.955904181,"remaining_time":85.94447591},
{"learn":[7168.624299],"iteration":11,"passed_time":1.014544048,"remaining_time":83.53079332},
{"learn":[7042.290578],"iteration":12,"passed_time":1.135207214,"remaining_time":86.18842462},
{"learn":[6926.68485],"iteration":13,"passed_time":1.235413262,"remaining_time":87.00839117},,
{"learn":[6712.103876],"iteration":14,"passed_time":1.30242889,"remaining_time":85.52616378},
{"learn":[6581.751854],"iteration":15,"passed_time":1.427692323,"remaining_time":87.80307786},
{"learn":[6462.624544],"iteration":16,"passed_time":1.520956415,"remaining_time":87.94706801,,
{"learn":[6355.330149],"iteration":17,"passed_time":1.662682387,"remaining_time":90.70856135,,
{"learn":[6234.855023],"iteration":18,"passed_time":1.7602402,"remaining_time":90.88398084},
{"learn":[6121.231886],"iteration":19,"passed_time":1.842201485,"remaining_time":90.26787277},
{"learn":[6016.666865],"iteration":20,"passed_time":1.921040786,"remaining_time":89.55709189},
{"learn":[5915.534495],"iteration":21,"passed_time":1.99110744,"remaining_time":88.51377622},
{"learn":[5817.34965],"iteration":22,"passed_time":2.050199813,"remaining_time":87.08892251},
{"learn":[5720.567479],"iteration":23,"passed_time":2.180619691,"remaining_time":88.67853409},
{"learn":[5612.769513],"iteration":24,"passed_time":2.280941201,"remaining_time":88.95670683},
{"learn":[5517.935027],"iteration":25,"passed_time":2.3527101,"remaining_time":88.13613991},
{"learn":[5418.895572],"iteration":26,"passed_time":2.409718191,"remaining_time":86.83910369},
{"learn":[5324.095532],"iteration":27,"passed_time":2.501628537,"remaining_time":86.84224777},
{"learn":[5223.911601],"iteration":28,"passed_time":2.622703171,"remaining_time":87.81533721},
{"learn":[5130.138102],"iteration":29,"passed_time":2.772411598,"remaining_time":89.64130834},
{"learn":[5036.816516],"iteration":30,"passed_time":2.894499088,"remaining_time":90.47643923},
{"learn":[4958.615913],"iteration":31,"passed_time":2.992713183,"remaining_time":90.52957377},
{"learn":[4875.452732],"iteration":32,"passed_time":3.102147593,"remaining_time":90.90232493},
{"learn":[4797.373991],"iteration":33,"passed_time":3.214388761,"remaining_time":91.32645714},
{"learn":[4724.600306],"iteration":34,"passed_time":3.302244639,"remaining_time":91.04760219},
{"learn":[4647.028491],"iteration":35,"passed_time":3.423886319,"remaining_time":91.68406697},
{"learn":[4577.97917],"iteration":36,"passed_time":3.552874673,"remaining_time":92.47076515},
{"learn":[4502.880591],"iteration":37,"passed_time":3.62592968,"remaining_time":91.79327243},
{"learn":[4437.026847],"iteration":38,"passed_time":3.689179205,"remaining_time":90.90515939},
{"learn":[4370.03213],"iteration":39,"passed_time":3.762325305,"remaining_time":90.29580732},
{"learn":[4299.338158],"iteration":40,"passed_time":3.872136567,"remaining_time":90.57021873},
{"learn":[4226.672149],"iteration":41,"passed_time":3.917920977,"remaining_time":89.3659118},
{"learn":[4150.547627],"iteration":42,"passed_time":3.984402847,"remaining_time":88.67612848},
{"learn":[4077.023144],"iteration":43,"passed_time":4.064008506,"remaining_time":88.29982118},
{"learn":[4008.027761],"iteration":44,"passed_time":4.158498476,"remaining_time":88.25257877},
{"learn":[3939.205263],"iteration":45,"passed_time":4.244501782,"remaining_time":88.02727609},
{"learn":[3883.5364],"iteration":46,"passed_time":4.307847567,"remaining_time":87.34848366},
{"learn":[3816.395096],"iteration":47,"passed_time":4.339239696,"remaining_time":86.06158731},
{"learn":[3757.161335],"iteration":48,"passed_time":4.397418288,"remaining_time":85.34581207},
{"learn":[3700.442713],"iteration":49,"passed_time":4.466636631,"remaining_time":84.86609599},
{"learn":[3639.205191],"iteration":50,"passed_time":4.540071948,"remaining_time":84.48094664},
{"learn":[3583.87085],"iteration":51,"passed_time":4.640474459,"remaining_time":84.59941899},
{"learn":[3529.810604],"iteration":52,"passed_time":4.713705238,"remaining_time":84.22412944},
{"learn":[3470.275285],"iteration":53,"passed_time":4.783293902,"remaining_time":83.7962228},
{"learn":[3420.688076],"iteration":54,"passed_time":4.815318596,"remaining_time":82.73592861},
{"learn":[3364.38913],"iteration":55,"passed_time":4.877774112,"remaining_time":82.22533503},
{"learn":[3312.541432],"iteration":56,"passed_time":4.958476145,"remaining_time":82.03233341},
{"learn":[3260.799764],"iteration":57,"passed_time":5.037784044,"remaining_time":81.82056155},
{"learn":[3214.164386],"iteration":58,"passed_time":5.088280018,"remaining_time":81.15375419},
{"learn":[3161.21153],"iteration":59,"passed_time":5.146014522,"remaining_time":80.62089418},
{"learn":[3123.062512],"iteration":60,"passed_time":5.198912707,"remaining_time":80.02916446},
{"learn":[3074.75901],"iteration":61,"passed_time":5.256419538,"remaining_time":79.52454076},
{"learn":[3030.113985],"iteration":62,"passed_time":5.31007717,"remaining_time":78.97686204},
{"learn":[2987.055356],"iteration":63,"passed_time":5.367116117,"remaining_time":78.49407321},
{"learn":[2949.620324],"iteration":64,"passed_time":5.423402003,"remaining_time":78.01355189},
{"learn":[2911.115074],"iteration":65,"passed_time":5.491362787,"remaining_time":77.71110369},
{"learn":[2866.440155],"iteration":66,"passed_time":5.567699521,"remaining_time":77.53229333},
{"learn":[2823.897472],"iteration":67,"passed_time":5.626924152,"remaining_time":77.12196043},
{"learn":[2785.797634],"iteration":68,"passed_time":5.71330598,"remaining_time":77.08822996},
{"learn":[2740.578088],"iteration":69,"passed_time":5.771677117,"remaining_time":76.68085312},
{"learn":[2700.437204],"iteration":70,"passed_time":5.81875606,"remaining_time":76.13555465},
{"learn":[2666.184938],"iteration":71,"passed_time":5.905234489,"remaining_time":76.11191119},
{"learn":[2629.137771],"iteration":72,"passed_time":5.936018058,"remaining_time":75.37929781},
{"learn":[2591.861782],"iteration":73,"passed_time":5.984263839,"remaining_time":74.88416641},
{"learn":[2556.242863],"iteration":74,"passed_time":6.071045729,"remaining_time":74.87623066},
{"learn":[2522.974143],"iteration":75,"passed_time":6.132051883,"remaining_time":74.55284131},
{"learn":[2486.144542],"iteration":76,"passed_time":6.214621877,"remaining_time":74.49475315},
{"learn":[2450.386846],"iteration":77,"passed_time":6.272981539,"remaining_time":74.1498587},
{"learn":[2417.6572],"iteration":78,"passed_time":6.349204516,"remaining_time":74.02047291},
{"learn":[2385.841494],"iteration":79,"passed_time":6.451017553,"remaining_time":74.18670186},
{"learn":[2351.788251],"iteration":80,"passed_time":6.506555098,"remaining_time":73.82128562},
{"learn":[2320.349407],"iteration":81,"passed_time":6.564034298,"remaining_time":73.48516446},
{"learn":[2288.848722],"iteration":82,"passed_time":6.613278293,"remaining_time":73.06477343},
{"learn":[2259.928055],"iteration":83,"passed_time":6.669022446,"remaining_time":72.72410191},
{"learn":[2231.803116],"iteration":84,"passed_time":6.736682143,"remaining_time":72.5184019},
{"learn":[2200.766105],"iteration":85,"passed_time":6.787586291,"remaining_time":72.13783569},
{"learn":[2175.326542],"iteration":86,"passed_time":6.859169321,"remaining_time":71.98185736},
{"learn":[2149.806066],"iteration":87,"passed_time":6.921144545,"remaining_time":71.72822529},
{"learn":[2119.431893],"iteration":88,"passed_time":7.018483087,"remaining_time":71.84087745},
{"learn":[2091.83908],"iteration":89,"passed_time":7.076329429,"remaining_time":71.54955312},
{"learn":[2064.287869],"iteration":90,"passed_time":7.140014195,"remaining_time":71.32168026},
{"learn":[2042.666562],"iteration":91,"passed_time":7.201019102,"remaining_time":71.07092766},
{"learn":[2017.166733],"iteration":92,"passed_time":7.27507072,"remaining_time":70.95149616},
{"learn":[1992.821166],"iteration":93,"passed_time":7.331695852,"remaining_time":70.66506853},
{"learn":[1973.646647],"iteration":94,"passed_time":7.425786728,"remaining_time":70.74038936},
{"learn":[1949.278567],"iteration":95,"passed_time":7.512939218,"remaining_time":70.74684431},
{"learn":[1926.774229],"iteration":96,"passed_time":7.593306016,"remaining_time":70.68819931},
{"learn":[1905.751526],"iteration":97,"passed_time":7.651169626,"remaining_time":70.42198983},
{"learn":[1882.663791],"iteration":98,"passed_time":7.719160637,"remaining_time":70.25215893},
{"learn":[1863.602813],"iteration":99,"passed_time":7.795967965,"remaining_time":70.16371168},
{"learn":[1842.358998],"iteration":100,"passed_time":7.861524179,"remaining_time":69.97534888},
{"learn":[1826.365381],"iteration":101,"passed_time":7.965218155,"remaining_time":70.12515592},
{"learn":[1805.763363],"iteration":102,"passed_time":8.017274974,"remaining_time":69.82034613},
{"learn":[1786.254895],"iteration":103,"passed_time":8.085186157,"remaining_time":69.65698843},
{"learn":[1768.676407],"iteration":104,"passed_time":8.170129498,"remaining_time":69.64062762},
{"learn":[1748.986417],"iteration":105,"passed_time":8.224444938,"remaining_time":69.36465825},
{"learn":[1731.066369],"iteration":106,"passed_time":8.290518662,"remaining_time":69.19096416},
{"learn":[1714.396927],"iteration":107,"passed_time":8.38550821,"remaining_time":69.25808632},
{"learn":[1696.815695],"iteration":108,"passed_time":8.45848189,"remaining_time":69.1422694},
{"learn":[1676.000953],"iteration":109,"passed_time":8.513760849,"remaining_time":68.88406505},
{"learn":[1656.94423],"iteration":110,"passed_time":8.611637403,"remaining_time":68.97068155},
{"learn":[1641.892263],"iteration":111,"passed_time":8.664692173,"remaining_time":68.6986308},
{"learn":[1624.40633],"iteration":112,"passed_time":8.739997951,"remaining_time":68.60511666},
{"learn":[1611.337212],"iteration":113,"passed_time":8.817244684,"remaining_time":68.52700693},
{"learn":[1597.509144],"iteration":114,"passed_time":8.890649629,"remaining_time":68.41934715},
{"learn":[1580.583995],"iteration":115,"passed_time":8.943395344,"remaining_time":68.15484038},
{"learn":[1566.460119],"iteration":116,"passed_time":9.016850029,"remaining_time":68.05024423},
{"learn":[1554.721727],"iteration":117,"passed_time":9.073921006,"remaining_time":67.82371464},
{"learn":[1540.253768],"iteration":118,"passed_time":9.150826873,"remaining_time":67.74687794},
{"learn":[1528.273675],"iteration":119,"passed_time":9.222352231,"remaining_time":67.63058303},
{"learn":[1512.411349],"iteration":120,"passed_time":9.308154065,"remaining_time":67.61873903},
{"learn":[1498.90712],"iteration":121,"passed_time":9.392652421,"remaining_time":67.59630185},
{"learn":[1485.520245],"iteration":122,"passed_time":9.495215487,"remaining_time":67.70165839},
{"learn":[1470.355358],"iteration":123,"passed_time":9.562799215,"remaining_time":67.55654929},
{"learn":[1457.531856],"iteration":124,"passed_time":9.64259773,"remaining_time":67.49818411},
{"learn":[1443.228477],"iteration":125,"passed_time":9.744549051,"remaining_time":67.59314183},
{"learn":[1428.588747],"iteration":126,"passed_time":9.800450024,"remaining_time":67.3684478},
{"learn":[1416.115484],"iteration":127,"passed_time":9.853790924,"remaining_time":67.12895067},
{"learn":[1404.963643],"iteration":128,"passed_time":9.957691275,"remaining_time":67.23371396},
{"learn":[1390.155157],"iteration":129,"passed_time":10.02832186,"remaining_time":67.11261552},
{"learn":[1378.892674],"iteration":130,"passed_time":10.08811934,"remaining_time":66.92042524},
{"learn":[1366.789194],"iteration":131,"passed_time":10.15214225,"remaining_time":66.75802632},
{"learn":[1356.505303],"iteration":132,"passed_time":10.21430042,"remaining_time":66.58495085},
{"learn":[1343.58012],"iteration":133,"passed_time":10.28831526,"remaining_time":66.49015682},
{"learn":[1332.833989],"iteration":134,"passed_time":10.32770649,"remaining_time":66.17382309},
{"learn":[1321.017064],"iteration":135,"passed_time":10.39377712,"remaining_time":66.03105464},
{"learn":[1311.575242],"iteration":136,"passed_time":10.43332648,"remaining_time":65.72234123},
{"learn":[1302.178156],"iteration":137,"passed_time":10.52479676,"remaining_time":65.74184641},
{"learn":[1293.294098],"iteration":138,"passed_time":10.58881408,"remaining_time":65.58970447},
{"learn":[1282.443985],"iteration":139,"passed_time":10.64166878,"remaining_time":65.3702511},
{"learn":[1273.682317],"iteration":140,"passed_time":10.71187589,"remaining_time":65.25887512},
{"learn":[1264.173365],"iteration":141,"passed_time":10.77776831,"remaining_time":65.12200849},
{"learn":[1256.684538],"iteration":142,"passed_time":10.82896958,"remaining_time":64.89809039},
{"learn":[1247.541982],"iteration":143,"passed_time":10.90085764,"remaining_time":64.79954265},
{"learn":[1239.407598],"iteration":144,"passed_time":10.95297097,"remaining_time":64.58475984},
{"learn":[1229.662999],"iteration":145,"passed_time":11.03589074,"remaining_time":64.552402},
{"learn":[1218.384612],"iteration":146,"passed_time":11.09467101,"remaining_time":64.37928146},
{"learn":[1209.272975],"iteration":147,"passed_time":11.12803503,"remaining_time":64.06139085},
{"learn":[1198.354704],"iteration":148,"passed_time":11.18108041,"remaining_time":63.85972769},
{"learn":[1191.10614],"iteration":149,"passed_time":11.28276854,"remaining_time":63.9356884},
{"learn":[1183.450967],"iteration":150,"passed_time":11.33480644,"remaining_time":63.73013685},
{"learn":[1176.082662],"iteration":151,"passed_time":11.38393778,"remaining_time":63.51038974},
{"learn":[1168.562785],"iteration":152,"passed_time":11.45655134,"remaining_time":63.42286919},
{"learn":[1160.709536],"iteration":153,"passed_time":11.56034134,"remaining_time":63.50681022},
{"learn":[1151.119102],"iteration":154,"passed_time":11.66027858,"remaining_time":63.56732515},
{"learn":[1143.58212],"iteration":155,"passed_time":11.71436125,"remaining_time":63.37769806},
{"learn":[1139.256102],"iteration":156,"passed_time":11.78701631,"remaining_time":63.28952067},
{"learn":[1131.316345],"iteration":157,"passed_time":11.85824346,"remaining_time":63.19393034},
{"learn":[1124.487753],"iteration":158,"passed_time":11.8900472,"remaining_time":62.89012386},
{"learn":[1115.839818],"iteration":159,"passed_time":11.96318736,"remaining_time":62.80673365},
{"learn":[1107.100772],"iteration":160,"passed_time":12.01029023,"remaining_time":62.58778575},
{"learn":[1098.202022],"iteration":161,"passed_time":12.06266919,"remaining_time":62.39825171},
{"learn":[1090.105519],"iteration":162,"passed_time":12.14076624,"remaining_time":62.34246224},
{"learn":[1083.691656],"iteration":163,"passed_time":12.20178362,"remaining_time":62.19933603},
{"learn":[1076.644513],"iteration":164,"passed_time":12.25860795,"remaining_time":62.03598568},
{"learn":[1069.569207],"iteration":165,"passed_time":12.31614752,"remaining_time":61.87751222},
{"learn":[1061.055915],"iteration":166,"passed_time":12.38879777,"remaining_time":61.79562003},
{"learn":[1055.498092],"iteration":167,"passed_time":12.48162791,"remaining_time":61.8137763},
{"learn":[1048.228668],"iteration":168,"passed_time":12.55519189,"remaining_time":61.73588438},
{"learn":[1040.037796],"iteration":169,"passed_time":12.63311012,"remaining_time":61.67930237},
{"learn":[1033.377956],"iteration":170,"passed_time":12.70061969,"remaining_time":61.57201009},
{"learn":[1026.593712],"iteration":171,"passed_time":12.79832589,"remaining_time":61.61054556},
{"learn":[1020.660794],"iteration":172,"passed_time":12.87676182,"remaining_time":61.55538741},
{"learn":[1014.744978],"iteration":173,"passed_time":12.94985666,"remaining_time":61.47460691},
{"learn":[1006.554779],"iteration":174,"passed_time":13.01155263,"remaining_time":61.34017668},
{"learn":[1000.290389],"iteration":175,"passed_time":13.05450797,"remaining_time":61.11883278},
{"learn":[993.7221131],"iteration":176,"passed_time":13.13107109,"remaining_time":61.05577121},
{"learn":[987.1073916],"iteration":177,"passed_time":13.20520857,"remaining_time":60.98135643},
{"learn":[979.9785604],"iteration":178,"passed_time":13.28148794,"remaining_time":60.91676871},
{"learn":[974.7787933],"iteration":179,"passed_time":13.34547946,"remaining_time":60.79607308},
{"learn":[968.3241169],"iteration":180,"passed_time":13.43240857,"remaining_time":60.77979346},
{"learn":[963.1329368],"iteration":181,"passed_time":13.49193675,"remaining_time":60.63958386},
{"learn":[957.5143535],"iteration":182,"passed_time":13.54697797,"remaining_time":60.48022403},
{"learn":[949.2183658],"iteration":183,"passed_time":13.6211239,"remaining_time":60.40672338},
{"learn":[943.7646309],"iteration":184,"passed_time":13.68015275,"remaining_time":60.26661886},
{"learn":[938.1127036],"iteration":185,"passed_time":13.72019492,"remaining_time":60.04429388},
{"learn":[932.7856512],"iteration":186,"passed_time":13.76839297,"remaining_time":59.85937693},
{"learn":[928.333864],"iteration":187,"passed_time":13.83473017,"remaining_time":59.75426008},
{"learn":[920.9825649],"iteration":188,"passed_time":13.91470464,"remaining_time":59.70807124},
{"learn":[915.0242925],"iteration":189,"passed_time":13.9923954,"remaining_time":59.65179091},
{"learn":[908.8291158],"iteration":190,"passed_time":14.05232475,"remaining_time":59.52005614},
{"learn":[903.2314622],"iteration":191,"passed_time":14.12320911,"remaining_time":59.43517167},
{"learn":[896.6484983],"iteration":192,"passed_time":14.19316563,"remaining_time":59.34655265},
{"learn":[892.8333517],"iteration":193,"passed_time":14.26920974,"remaining_time":59.28341779},
{"learn":[888.3112823],"iteration":194,"passed_time":14.32992752,"remaining_time":59.1568803},
{"learn":[882.7636457],"iteration":195,"passed_time":14.3998375,"remaining_time":59.06872116},
{"learn":[876.5843266],"iteration":196,"passed_time":14.4666972,"remaining_time":58.96831395},
{"learn":[870.5330477],"iteration":197,"passed_time":14.52479797,"remaining_time":58.83276755},
{"learn":[865.2613077],"iteration":198,"passed_time":14.59105514,"remaining_time":58.73083},
{"learn":[859.9977589],"iteration":199,"passed_time":14.65809317,"remaining_time":58.63237269},
{"learn":[855.1356832],"iteration":200,"passed_time":14.75277054,"remaining_time":58.6440978},
{"learn":[849.3021393],"iteration":201,"passed_time":14.84245074,"remaining_time":58.63502818},
{"learn":[844.3182863],"iteration":202,"passed_time":14.88761088,"remaining_time":58.45037374},
{"learn":[838.8801951],"iteration":203,"passed_time":14.92385507,"remaining_time":58.23229724},
{"learn":[834.0869953],"iteration":204,"passed_time":14.98848615,"remaining_time":58.12608044},
{"learn":[828.3347046],"iteration":205,"passed_time":15.05000522,"remaining_time":58.00827256},
{"learn":[822.8433158],"iteration":206,"passed_time":15.08545728,"remaining_time":57.79114793},
{"learn":[818.5987827],"iteration":207,"passed_time":15.17530355,"remaining_time":57.7828866},
{"learn":[812.1780985],"iteration":208,"passed_time":15.25405662,"remaining_time":57.73186022},
{"learn":[808.6083216],"iteration":209,"passed_time":15.30828887,"remaining_time":57.5883248},
{"learn":[803.3500872],"iteration":210,"passed_time":15.36675905,"remaining_time":57.46148288},
{"learn":[799.2085932],"iteration":211,"passed_time":15.43509204,"remaining_time":57.37194588},
{"learn":[795.5413263],"iteration":212,"passed_time":15.46867903,"remaining_time":57.1542272},
{"learn":[789.9343544],"iteration":213,"passed_time":15.53561225,"remaining_time":57.06070667},
{"learn":[785.0935007],"iteration":214,"passed_time":15.63164646,"remaining_time":57.07368591},
{"learn":[780.2074309],"iteration":215,"passed_time":15.68262086,"remaining_time":56.92210536},
{"learn":[775.6411783],"iteration":216,"passed_time":15.74359563,"remaining_time":56.80753629},
{"learn":[770.3342366],"iteration":217,"passed_time":15.81376003,"remaining_time":56.7264236},
{"learn":[765.6663966],"iteration":218,"passed_time":15.86669185,"remaining_time":56.58395587},
{"learn":[762.7676804],"iteration":219,"passed_time":15.90799669,"remaining_time":56.40107919},
{"learn":[757.2863348],"iteration":220,"passed_time":15.99751541,"remaining_time":56.38943216},
{"learn":[754.3398422],"iteration":221,"passed_time":16.05061222,"remaining_time":56.24944283},
{"learn":[750.3625324],"iteration":222,"passed_time":16.10697156,"remaining_time":56.12160045},
{"learn":[745.5847579],"iteration":223,"passed_time":16.17881415,"remaining_time":56.04803473},
{"learn":[742.8978921],"iteration":224,"passed_time":16.26745437,"remaining_time":56.03234284},
{"learn":[737.7878079],"iteration":225,"passed_time":16.31006786,"remaining_time":55.858374},
{"learn":[732.7100062],"iteration":226,"passed_time":16.35442615,"remaining_time":55.69150403},
{"learn":[726.7823991],"iteration":227,"passed_time":16.39888016,"remaining_time":55.52603282},
{"learn":[723.2314182],"iteration":228,"passed_time":16.47503726,"remaining_time":55.46835691},
{"learn":[718.9116955],"iteration":229,"passed_time":16.52701525,"remaining_time":55.32957278},
{"learn":[716.28557],"iteration":230,"passed_time":16.59015981,"remaining_time":55.22871383},
{"learn":[710.4980768],"iteration":231,"passed_time":16.68874477,"remaining_time":55.24549991},
{"learn":[706.5743658],"iteration":232,"passed_time":16.77466171,"remaining_time":55.21959455},
{"learn":[701.9999231],"iteration":233,"passed_time":16.80585843,"remaining_time":55.01404939},
{"learn":[698.3325208],"iteration":234,"passed_time":16.8775176,"remaining_time":54.94170622},
{"learn":[693.8593816],"iteration":235,"passed_time":16.94219269,"remaining_time":54.8467594},
{"learn":[691.4284114],"iteration":236,"passed_time":17.00200099,"remaining_time":54.73639983},
{"learn":[688.3108188],"iteration":237,"passed_time":17.05555234,"remaining_time":54.60643227},
{"learn":[685.0818564],"iteration":238,"passed_time":17.09871954,"remaining_time":54.44404005},
{"learn":[683.5369733],"iteration":239,"passed_time":17.14901039,"remaining_time":54.30519957},
{"learn":[678.4470803],"iteration":240,"passed_time":17.1853566,"remaining_time":54.123177},
{"learn":[672.968651],"iteration":241,"passed_time":17.21855998,"remaining_time":53.93251431},
{"learn":[668.6718871],"iteration":242,"passed_time":17.30713168,"remaining_time":53.91563245},
{"learn":[665.2550392],"iteration":243,"passed_time":17.38225439,"remaining_time":53.85649311},
{"learn":[660.5725405],"iteration":244,"passed_time":17.45602614,"remaining_time":53.79306015},
{"learn":[657.2087801],"iteration":245,"passed_time":17.54579378,"remaining_time":53.77857117},
{"learn":[653.5323125],"iteration":246,"passed_time":17.61196859,"remaining_time":53.69154796},
{"learn":[649.1048239],"iteration":247,"passed_time":17.67095333,"remaining_time":53.58289075},
{"learn":[646.2869958],"iteration":248,"passed_time":17.73635289,"remaining_time":53.49398},
{"learn":[641.1168144],"iteration":249,"passed_time":17.78664512,"remaining_time":53.35993537},
{"learn":[638.077918],"iteration":250,"passed_time":17.87306736,"remaining_time":53.33437232},
{"learn":[635.8671952],"iteration":251,"passed_time":17.95331049,"remaining_time":53.28998509},
{"learn":[632.7021104],"iteration":252,"passed_time":17.98686582,"remaining_time":53.10746549},
{"learn":[629.534709],"iteration":253,"passed_time":18.08354148,"remaining_time":53.11150373},
{"learn":[625.2583121],"iteration":254,"passed_time":18.14212883,"remaining_time":53.00347443},
{"learn":[621.2703218],"iteration":255,"passed_time":18.20521255,"remaining_time":52.90889899},
{"learn":[619.6511343],"iteration":256,"passed_time":18.25994787,"remaining_time":52.79043296},
{"learn":[615.4299256],"iteration":257,"passed_time":18.33146279,"remaining_time":52.72071858},
{"learn":[613.1567461],"iteration":258,"passed_time":18.40772691,"remaining_time":52.66457776},
{"learn":[608.2225071],"iteration":259,"passed_time":18.47000499,"remaining_time":52.56847574},
{"learn":[605.713762],"iteration":260,"passed_time":18.52543147,"remaining_time":52.45323318},
{"learn":[600.7251837],"iteration":261,"passed_time":18.5974991,"remaining_time":52.3853219},
{"learn":[597.4028159],"iteration":262,"passed_time":18.65263095,"remaining_time":52.26992019},
{"learn":[594.0897871],"iteration":263,"passed_time":18.74081407,"remaining_time":52.24711802},
{"learn":[590.3012438],"iteration":264,"passed_time":18.80487706,"remaining_time":52.15692316},
{"learn":[589.4774989],"iteration":265,"passed_time":18.87710653,"remaining_time":52.08945938},
{"learn":[587.5309323],"iteration":266,"passed_time":18.94994053,"remaining_time":52.02361951},
{"learn":[586.1860234],"iteration":267,"passed_time":19.00861533,"remaining_time":51.91905382},
{"learn":[582.4276993],"iteration":268,"passed_time":19.10465044,"remaining_time":51.91635491},
{"learn":[577.9166559],"iteration":269,"passed_time":19.20977042,"remaining_time":51.93752744},
{"learn":[577.2382332],"iteration":270,"passed_time":19.28276452,"remaining_time":51.87134809},
{"learn":[573.4583421],"iteration":271,"passed_time":19.36001597,"remaining_time":51.81651334},
{"learn":[571.898519],"iteration":272,"passed_time":19.43072013,"remaining_time":51.74407889},
{"learn":[570.4653674],"iteration":273,"passed_time":19.49639795,"remaining_time":51.6583391},
{"learn":[568.3861292],"iteration":274,"passed_time":19.56557821,"remaining_time":51.58197892},
{"learn":[566.5419947],"iteration":275,"passed_time":19.61193857,"remaining_time":51.44580987},
{"learn":[563.229675],"iteration":276,"passed_time":19.67755576,"remaining_time":51.36055169},
{"learn":[561.4696442],"iteration":277,"passed_time":19.73654189,"remaining_time":51.25821311},
{"learn":[558.6370579],"iteration":278,"passed_time":19.79103049,"remaining_time":51.14456266},
{"learn":[555.6744316],"iteration":279,"passed_time":19.86229565,"remaining_time":51.07447454},
{"learn":[553.4719672],"iteration":280,"passed_time":19.92379979,"remaining_time":50.9794023},
{"learn":[551.4114136],"iteration":281,"passed_time":19.99502795,"remaining_time":50.90932648},
{"learn":[548.2119348],"iteration":282,"passed_time":20.05986966,"remaining_time":50.82306201},
{"learn":[546.7319512],"iteration":283,"passed_time":20.12709017,"remaining_time":50.74294565},
{"learn":[542.9104721],"iteration":284,"passed_time":20.19448137,"remaining_time":50.663348},
{"learn":[539.9740131],"iteration":285,"passed_time":20.2421071,"remaining_time":50.53449114},
{"learn":[537.7076799],"iteration":286,"passed_time":20.32805188,"remaining_time":50.50139719},
{"learn":[534.0564778],"iteration":287,"passed_time":20.39152663,"remaining_time":50.41238528},
{"learn":[532.7157706],"iteration":288,"passed_time":20.46763217,"remaining_time":50.35462448},
{"learn":[529.8741477],"iteration":289,"passed_time":20.53781597,"remaining_time":50.28223909},
{"learn":[528.6916358],"iteration":290,"passed_time":20.58833211,"remaining_time":50.16195006},
{"learn":[525.044013],"iteration":291,"passed_time":20.65514429,"remaining_time":50.08165121},
{"learn":[522.3596891],"iteration":292,"passed_time":20.71070234,"remaining_time":49.97428857},
{"learn":[518.9426504],"iteration":293,"passed_time":20.77637135,"remaining_time":49.89155841},
{"learn":[515.6384659],"iteration":294,"passed_time":20.88204314,"remaining_time":49.90454377},
{"learn":[513.4502364],"iteration":295,"passed_time":20.95819255,"remaining_time":49.846512},
{"learn":[508.9504474],"iteration":296,"passed_time":21.02616914,"remaining_time":49.76901314},
{"learn":[508.0778485],"iteration":297,"passed_time":21.07168678,"remaining_time":49.63867155},
{"learn":[505.9298897],"iteration":298,"passed_time":21.12167513,"remaining_time":49.51937882},
{"learn":[503.701962],"iteration":299,"passed_time":21.17097222,"remaining_time":49.39893518},
{"learn":[502.2603652],"iteration":300,"passed_time":21.22488091,"remaining_time":49.2896736},
{"learn":[499.9531325],"iteration":301,"passed_time":21.27725332,"remaining_time":49.17722787},
{"learn":[496.6188249],"iteration":302,"passed_time":21.36423634,"remaining_time":49.14479449},
{"learn":[492.901015],"iteration":303,"passed_time":21.40881498,"remaining_time":49.01491851},
{"learn":[491.1744132],"iteration":304,"passed_time":21.46201863,"remaining_time":48.90525556},
{"learn":[488.2246449],"iteration":305,"passed_time":21.55442854,"remaining_time":48.88488042},
{"learn":[487.1438854],"iteration":306,"passed_time":21.59749224,"remaining_time":48.75264535},
{"learn":[483.2939439],"iteration":307,"passed_time":21.66523739,"remaining_time":48.67644244},
{"learn":[480.4008296],"iteration":308,"passed_time":21.72994241,"remaining_time":48.59349581},
{"learn":[479.2522795],"iteration":309,"passed_time":21.77667857,"remaining_time":48.47067167},
{"learn":[475.7009439],"iteration":310,"passed_time":21.84801963,"remaining_time":48.40284735},
{"learn":[473.04071],"iteration":311,"passed_time":21.9104798,"remaining_time":48.31541699},
{"learn":[470.3471628],"iteration":312,"passed_time":21.9573481,"remaining_time":48.19392379},
{"learn":[469.1366677],"iteration":313,"passed_time":21.98623044,"remaining_time":48.03361173},
{"learn":[466.0717731],"iteration":314,"passed_time":22.05239715,"remaining_time":47.95521285},
{"learn":[462.8607821],"iteration":315,"passed_time":22.12606609,"remaining_time":47.89313039},
{"learn":[461.8256904],"iteration":316,"passed_time":22.18960191,"remaining_time":47.80914229},
{"learn":[458.9112408],"iteration":317,"passed_time":22.25508512,"remaining_time":47.72945927},
{"learn":[457.9555373],"iteration":318,"passed_time":22.31304525,"remaining_time":47.63380506},
{"learn":[454.9280976],"iteration":319,"passed_time":22.38935704,"remaining_time":47.57738372},
{"learn":[454.2134391],"iteration":320,"passed_time":22.43107566,"remaining_time":47.44766471},
{"learn":[452.6351431],"iteration":321,"passed_time":22.51016804,"remaining_time":47.39718612},
{"learn":[450.2727202],"iteration":322,"passed_time":22.57617298,"remaining_time":47.31909941},
{"learn":[446.635805],"iteration":323,"passed_time":22.65543959,"remaining_time":47.26875667},
{"learn":[443.8593107],"iteration":324,"passed_time":22.711224,"remaining_time":47.16946523},
{"learn":[440.575831],"iteration":325,"passed_time":22.76457532,"remaining_time":47.06541033},
{"learn":[438.8101788],"iteration":326,"passed_time":22.82602711,"remaining_time":46.97833714},
{"learn":[436.0850254],"iteration":327,"passed_time":22.91020632,"remaining_time":46.93798367},
{"learn":[432.8482591],"iteration":328,"passed_time":22.97992722,"remaining_time":46.86787588},
{"learn":[430.2424279],"iteration":329,"passed_time":23.05836984,"remaining_time":46.81547816},
{"learn":[429.3104559],"iteration":330,"passed_time":23.13207079,"remaining_time":46.75333946},
{"learn":[428.3727017],"iteration":331,"passed_time":23.18507826,"remaining_time":46.64949481},
{"learn":[427.2340408],"iteration":332,"passed_time":23.27344852,"remaining_time":46.61678727},
{"learn":[426.2208855],"iteration":333,"passed_time":23.31187825,"remaining_time":46.48416442},
{"learn":[425.6630409],"iteration":334,"passed_time":23.37543511,"remaining_time":46.40198312},
{"learn":[424.6402145],"iteration":335,"passed_time":23.429153,"remaining_time":46.30046902},
{"learn":[423.089623],"iteration":336,"passed_time":23.48590308,"remaining_time":46.20520397},
{"learn":[421.290343],"iteration":337,"passed_time":23.56669076,"remaining_time":46.15724641},
{"learn":[418.2368532],"iteration":338,"passed_time":23.6213238,"remaining_time":46.05809745},
{"learn":[415.4487001],"iteration":339,"passed_time":23.68948513,"remaining_time":45.98547113},
{"learn":[412.7799132],"iteration":340,"passed_time":23.73915406,"remaining_time":45.87713351},
{"learn":[411.9501345],"iteration":341,"passed_time":23.80780124,"remaining_time":45.80565269},
{"learn":[409.449919],"iteration":342,"passed_time":23.8601461,"remaining_time":45.70296207},
{"learn":[407.4806842],"iteration":343,"passed_time":23.91159836,"remaining_time":45.59886199},
{"learn":[404.8614399],"iteration":344,"passed_time":23.97019141,"remaining_time":45.50862428},
{"learn":[401.7773177],"iteration":345,"passed_time":24.03701159,"remaining_time":45.43412017},
{"learn":[399.0788373],"iteration":346,"passed_time":24.10586683,"remaining_time":45.36349004},
{"learn":[397.1761916],"iteration":347,"passed_time":24.17345609,"remaining_time":45.29049819},
{"learn":[396.3360918],"iteration":348,"passed_time":24.20891133,"remaining_time":45.15759678},
{"learn":[395.4472299],"iteration":349,"passed_time":24.26957705,"remaining_time":45.07207167},
{"learn":[392.499157],"iteration":350,"passed_time":24.3463907,"remaining_time":45.01654576},
{"learn":[389.8153108],"iteration":351,"passed_time":24.39156445,"remaining_time":44.90265273},
{"learn":[388.7839527],"iteration":352,"passed_time":24.46560811,"remaining_time":44.84206358},
{"learn":[385.8663223],"iteration":353,"passed_time":24.57194729,"remaining_time":44.84033319},
{"learn":[385.0770665],"iteration":354,"passed_time":24.64048462,"remaining_time":44.76933122},
{"learn":[382.3111688],"iteration":355,"passed_time":24.71609337,"remaining_time":44.71113519},
{"learn":[380.0494163],"iteration":356,"passed_time":24.77770091,"remaining_time":44.62762377},
{"learn":[379.341325],"iteration":357,"passed_time":24.87886797,"remaining_time":44.61517663},
{"learn":[377.306623],"iteration":358,"passed_time":24.91402559,"remaining_time":44.48437439},
{"learn":[374.7833407],"iteration":359,"passed_time":24.93620629,"remaining_time":44.3310334},
{"learn":[372.3443289],"iteration":360,"passed_time":24.99398646,"remaining_time":44.24143309},
{"learn":[370.6494679],"iteration":361,"passed_time":25.05352628,"remaining_time":44.15510985},
{"learn":[367.9733228],"iteration":362,"passed_time":25.11537386,"remaining_time":44.07298387},
{"learn":[367.3630941],"iteration":363,"passed_time":25.15290128,"remaining_time":43.94847586},
{"learn":[365.4309987],"iteration":364,"passed_time":25.19158891,"remaining_time":43.8264629},
{"learn":[363.0753246],"iteration":365,"passed_time":25.26104184,"remaining_time":43.75819816},
{"learn":[360.7690884],"iteration":366,"passed_time":25.30575555,"remaining_time":43.64725685},
{"learn":[359.6669636],"iteration":367,"passed_time":25.35919136,"remaining_time":43.55165472},
{"learn":[357.6541848],"iteration":368,"passed_time":25.41523784,"remaining_time":43.46074547},
{"learn":[355.6826511],"iteration":369,"passed_time":25.44195326,"remaining_time":43.32008258},
{"learn":[354.1895799],"iteration":370,"passed_time":25.50450334,"remaining_time":43.24078868},
{"learn":[352.4186872],"iteration":371,"passed_time":25.57806836,"remaining_time":43.18017992},
{"learn":[351.0588669],"iteration":372,"passed_time":25.63970417,"remaining_time":43.0994491},
{"learn":[349.7132536],"iteration":373,"passed_time":25.70119756,"remaining_time":43.01858201},
{"learn":[349.1001843],"iteration":374,"passed_time":25.77165123,"remaining_time":42.95275204},
{"learn":[347.0185516],"iteration":375,"passed_time":25.8454684,"remaining_time":42.89247947},
{"learn":[346.307457],"iteration":376,"passed_time":25.87238505,"remaining_time":42.75463099},
{"learn":[343.9629778],"iteration":377,"passed_time":25.92932086,"remaining_time":42.66676607},
{"learn":[341.985939],"iteration":378,"passed_time":25.98289936,"remaining_time":42.57356333},
{"learn":[341.3941216],"iteration":379,"passed_time":26.03537937,"remaining_time":42.47877686},
{"learn":[339.7034196],"iteration":380,"passed_time":26.07662228,"remaining_time":42.36595588},
{"learn":[336.8825985],"iteration":381,"passed_time":26.15851455,"remaining_time":42.31927223},
{"learn":[335.6474231],"iteration":382,"passed_time":26.26871858,"remaining_time":42.318014},
{"learn":[335.0450297],"iteration":383,"passed_time":26.3535841,"remaining_time":42.27554115},
{"learn":[333.0522176],"iteration":384,"passed_time":26.40962616,"remaining_time":42.18680543},
{"learn":[331.2961442],"iteration":385,"passed_time":26.50921362,"remaining_time":42.16750561},
{"learn":[329.0178341],"iteration":386,"passed_time":26.59018864,"remaining_time":42.11830913},
{"learn":[327.2209418],"iteration":387,"passed_time":26.66960481,"remaining_time":42.06649006},
{"learn":[324.9538263],"iteration":388,"passed_time":26.75433242,"remaining_time":42.02287175},
{"learn":[322.9352668],"iteration":389,"passed_time":26.810604,"remaining_time":41.93453446},
{"learn":[320.7072627],"iteration":390,"passed_time":26.87794651,"remaining_time":41.86360466},
{"learn":[319.73314],"iteration":391,"passed_time":26.93852955,"remaining_time":41.78220909},
{"learn":[319.2095677],"iteration":392,"passed_time":27.01034658,"remaining_time":41.71827067},
{"learn":[317.1393987],"iteration":393,"passed_time":27.09230328,"remaining_time":41.66988778},
{"learn":[315.1305602],"iteration":394,"passed_time":27.16085772,"remaining_time":41.6008074},
{"learn":[313.1388491],"iteration":395,"passed_time":27.20855499,"remaining_time":41.4999172},
{"learn":[311.5332993],"iteration":396,"passed_time":27.25628997,"remaining_time":41.39935227},
{"learn":[309.0863161],"iteration":397,"passed_time":27.2880435,"remaining_time":41.27487987},
{"learn":[308.0959181],"iteration":398,"passed_time":27.32820508,"remaining_time":41.16353698},
{"learn":[307.1486983],"iteration":399,"passed_time":27.41230898,"remaining_time":41.11846347},
{"learn":[304.8604544],"iteration":400,"passed_time":27.44194073,"remaining_time":40.99182667},
{"learn":[304.1391068],"iteration":401,"passed_time":27.49114153,"remaining_time":40.89478268},
{"learn":[303.1594597],"iteration":402,"passed_time":27.54002523,"remaining_time":40.79750636},
{"learn":[302.1781566],"iteration":403,"passed_time":27.59629866,"remaining_time":40.7113713},
{"learn":[300.9088034],"iteration":404,"passed_time":27.65862229,"remaining_time":40.63427225},
{"learn":[299.3070888],"iteration":405,"passed_time":27.74736975,"remaining_time":40.59590549},
{"learn":[297.1870269],"iteration":406,"passed_time":27.81053116,"remaining_time":40.52001224},
{"learn":[295.8989573],"iteration":407,"passed_time":27.86523738,"remaining_time":40.43191307},
{"learn":[294.601647],"iteration":408,"passed_time":27.95396959,"remaining_time":40.39314432},
{"learn":[293.1950692],"iteration":409,"passed_time":28.05827141,"remaining_time":40.37653691},
{"learn":[291.7096667],"iteration":410,"passed_time":28.11190788,"remaining_time":40.28689475},
{"learn":[291.3399641],"iteration":411,"passed_time":28.16578777,"remaining_time":40.19777477},
{"learn":[289.4515678],"iteration":412,"passed_time":28.22402241,"remaining_time":40.11501491},
{"learn":[288.2355005],"iteration":413,"passed_time":28.28765942,"remaining_time":40.04002034},
{"learn":[287.1448694],"iteration":414,"passed_time":28.36654297,"remaining_time":39.98657261},
{"learn":[286.1640622],"iteration":415,"passed_time":28.43391428,"remaining_time":39.9168412},
{"learn":[284.4072922],"iteration":416,"passed_time":28.50202852,"remaining_time":39.84815978},
{"learn":[282.6653531],"iteration":417,"passed_time":28.55293694,"remaining_time":39.75552464},
{"learn":[280.9478051],"iteration":418,"passed_time":28.59056445,"remaining_time":39.6446729},
{"learn":[278.7107145],"iteration":419,"passed_time":28.65031447,"remaining_time":39.56471999},
{"learn":[278.3350708],"iteration":420,"passed_time":28.70073699,"remaining_time":39.47203496},
{"learn":[276.7094761],"iteration":421,"passed_time":28.77365063,"remaining_time":39.4103556},
{"learn":[275.0203506],"iteration":422,"passed_time":28.86456279,"remaining_time":39.37317431},
{"learn":[273.3268346],"iteration":423,"passed_time":28.91121103,"remaining_time":39.27560743},
{"learn":[271.5601713],"iteration":424,"passed_time":28.96846758,"remaining_time":39.19263261},
{"learn":[270.3648097],"iteration":425,"passed_time":29.01620223,"remaining_time":39.09694855},
{"learn":[269.0755045],"iteration":426,"passed_time":29.08504306,"remaining_time":39.02981188},
{"learn":[267.5243616],"iteration":427,"passed_time":29.12744515,"remaining_time":38.92733324},
{"learn":[265.4904332],"iteration":428,"passed_time":29.22550592,"remaining_time":38.8992165},
{"learn":[264.1400343],"iteration":429,"passed_time":29.28896247,"remaining_time":38.82490374},
{"learn":[262.6222462],"iteration":430,"passed_time":29.35428011,"remaining_time":38.75309833},
{"learn":[261.4129925],"iteration":431,"passed_time":29.39786458,"remaining_time":38.65274787},
{"learn":[260.7605045],"iteration":432,"passed_time":29.43055741,"remaining_time":38.53839735},
{"learn":[260.1834479],"iteration":433,"passed_time":29.53608493,"remaining_time":38.5194103},
{"learn":[258.8583903],"iteration":434,"passed_time":29.59400809,"remaining_time":38.43819442},
{"learn":[257.4479446],"iteration":435,"passed_time":29.65854871,"remaining_time":38.36564557},
{"learn":[256.1554879],"iteration":436,"passed_time":29.72987621,"remaining_time":38.30187713},
{"learn":[254.7346446],"iteration":437,"passed_time":29.80669413,"remaining_time":38.24511896},
{"learn":[253.347318],"iteration":438,"passed_time":29.87131039,"remaining_time":38.17267683},
{"learn":[252.1479896],"iteration":439,"passed_time":29.92601215,"remaining_time":38.08765183},
{"learn":[250.9841742],"iteration":440,"passed_time":29.98155221,"remaining_time":38.00382695},
{"learn":[250.3645257],"iteration":441,"passed_time":30.03636614,"remaining_time":37.91921337},
{"learn":[249.4602949],"iteration":442,"passed_time":30.12413455,"remaining_time":37.87616918},
{"learn":[247.9236487],"iteration":443,"passed_time":30.17346485,"remaining_time":37.78478932},
{"learn":[247.203496],"iteration":444,"passed_time":30.25314941,"remaining_time":37.73145601},
{"learn":[246.0329464],"iteration":445,"passed_time":30.33483086,"remaining_time":37.68048497},
{"learn":[244.6226938],"iteration":446,"passed_time":30.43254126,"remaining_time":37.64920652},
{"learn":[243.8543007],"iteration":447,"passed_time":30.52337089,"remaining_time":37.60915342},
{"learn":[242.5529409],"iteration":448,"passed_time":30.58777922,"remaining_time":37.53645067},
{"learn":[241.7023895],"iteration":449,"passed_time":30.67124509,"remaining_time":37.48707734},
{"learn":[240.7453048],"iteration":450,"passed_time":30.75889595,"remaining_time":37.44264718},
{"learn":[239.5809887],"iteration":451,"passed_time":30.84030269,"remaining_time":37.39045547},
{"learn":[238.336649],"iteration":452,"passed_time":30.90546305,"remaining_time":37.31851719},
{"learn":[237.385709],"iteration":453,"passed_time":30.97808678,"remaining_time":37.25558454},
{"learn":[235.9474394],"iteration":454,"passed_time":31.05023223,"remaining_time":37.19203641},
{"learn":[235.2064654],"iteration":455,"passed_time":31.08879821,"remaining_time":37.08839085},
{"learn":[233.9232784],"iteration":456,"passed_time":31.16032124,"remaining_time":37.02418914},
{"learn":[233.1016764],"iteration":457,"passed_time":31.21967382,"remaining_time":36.94555286},
{"learn":[232.3532599],"iteration":458,"passed_time":31.29552618,"remaining_time":36.88644807},
{"learn":[231.5070214],"iteration":459,"passed_time":31.37305752,"remaining_time":36.82924143},
{"learn":[229.8489936],"iteration":460,"passed_time":31.42371331,"remaining_time":36.7405238},
{"learn":[228.6653188],"iteration":461,"passed_time":31.46081467,"remaining_time":36.63618678},
{"learn":[228.2661195],"iteration":462,"passed_time":31.52926555,"remaining_time":36.56850022},
{"learn":[226.891414],"iteration":463,"passed_time":31.61259948,"remaining_time":36.51800285},
{"learn":[225.961853],"iteration":464,"passed_time":31.66138824,"remaining_time":36.42761873},
{"learn":[225.2501315],"iteration":465,"passed_time":31.71533254,"remaining_time":36.34332098},
{"learn":[224.7102733],"iteration":466,"passed_time":31.7866662,"remaining_time":36.27900018},
{"learn":[223.3489683],"iteration":467,"passed_time":31.87288362,"remaining_time":36.23156856},
{"learn":[221.7865842],"iteration":468,"passed_time":31.93879506,"remaining_time":36.16098118},
{"learn":[221.3703345],"iteration":469,"passed_time":32.03121271,"remaining_time":36.12030369},
{"learn":[220.0278177],"iteration":470,"passed_time":32.11379222,"remaining_time":36.06835687},
{"learn":[219.6216051],"iteration":471,"passed_time":32.1686538,"remaining_time":35.98527375},
{"learn":[218.2941377],"iteration":472,"passed_time":32.22783377,"remaining_time":35.90712135},
{"learn":[217.4489094],"iteration":473,"passed_time":32.29066202,"remaining_time":35.83309751},
{"learn":[217.0706228],"iteration":474,"passed_time":32.34368075,"remaining_time":35.74827872},
{"learn":[216.551998],"iteration":475,"passed_time":32.42837972,"remaining_time":35.69846843},
{"learn":[215.6677925],"iteration":476,"passed_time":32.46563044,"remaining_time":35.59648788},
{"learn":[214.5987467],"iteration":477,"passed_time":32.536884,"remaining_time":35.53191098},
{"learn":[213.4513948],"iteration":478,"passed_time":32.55583255,"remaining_time":35.41041494},
{"learn":[212.1304903],"iteration":479,"passed_time":32.60863591,"remaining_time":35.32602223},
{"learn":[211.5074938],"iteration":480,"passed_time":32.67968931,"remaining_time":35.2614527},
{"learn":[210.882635],"iteration":481,"passed_time":32.73112482,"remaining_time":35.17577314},
{"learn":[209.9171435],"iteration":482,"passed_time":32.78669254,"remaining_time":35.09465847},
{"learn":[208.8616308],"iteration":483,"passed_time":32.8697927,"remaining_time":35.04300213},
{"learn":[208.5178493],"iteration":484,"passed_time":32.93538312,"remaining_time":34.97262331},
{"learn":[207.9489304],"iteration":485,"passed_time":32.99473268,"remaining_time":34.89566378},
{"learn":[206.5891267],"iteration":486,"passed_time":33.04909864,"remaining_time":34.8135269},
{"learn":[205.4174932],"iteration":487,"passed_time":33.14683981,"remaining_time":34.77701226},
{"learn":[203.9687202],"iteration":488,"passed_time":33.20493391,"remaining_time":34.69881642},
{"learn":[202.9583919],"iteration":489,"passed_time":33.27875064,"remaining_time":34.63706699},
{"learn":[202.1452415],"iteration":490,"passed_time":33.37431723,"remaining_time":34.59781562},
{"learn":[200.8834819],"iteration":491,"passed_time":33.43162573,"remaining_time":34.51883307},
{"learn":[199.6024674],"iteration":492,"passed_time":33.51935028,"remaining_time":34.47121824},
{"learn":[198.7947745],"iteration":493,"passed_time":33.59283958,"remaining_time":34.40885998},
{"learn":[198.4801445],"iteration":494,"passed_time":33.6521206,"remaining_time":34.33196142},
{"learn":[197.8795715],"iteration":495,"passed_time":33.67458298,"remaining_time":34.21772142},
{"learn":[197.6913617],"iteration":496,"passed_time":33.74174149,"remaining_time":34.14908646},
{"learn":[196.9141638],"iteration":497,"passed_time":33.80301904,"remaining_time":34.07452923},
{"learn":[196.4039134],"iteration":498,"passed_time":33.89261927,"remaining_time":34.02846143},
{"learn":[194.9520122],"iteration":499,"passed_time":33.96276135,"remaining_time":33.96276135},
{"learn":[194.3251979],"iteration":500,"passed_time":34.03896514,"remaining_time":33.90308105},
{"learn":[193.6563182],"iteration":501,"passed_time":34.07830473,"remaining_time":33.80676446},
{"learn":[192.6261297],"iteration":502,"passed_time":34.14242125,"remaining_time":33.73515579},
{"learn":[192.3572411],"iteration":503,"passed_time":34.18261221,"remaining_time":33.64003106},
{"learn":[191.3884272],"iteration":504,"passed_time":34.24157391,"remaining_time":33.56352294},
{"learn":[190.6416665],"iteration":505,"passed_time":34.32698372,"remaining_time":33.51290506},
{"learn":[189.6757816],"iteration":506,"passed_time":34.3765715,"remaining_time":33.42731706},
{"learn":[189.2378101],"iteration":507,"passed_time":34.48679713,"remaining_time":33.4005988},
{"learn":[188.4953424],"iteration":508,"passed_time":34.54764485,"remaining_time":33.32592067},
{"learn":[188.1094295],"iteration":509,"passed_time":34.61036439,"remaining_time":33.2530952},
{"learn":[186.9426975],"iteration":510,"passed_time":34.67653259,"remaining_time":33.18360946},
{"learn":[185.7502896],"iteration":511,"passed_time":34.72315355,"remaining_time":33.09550573},
{"learn":[184.7048686],"iteration":512,"passed_time":34.79456113,"remaining_time":33.03109409},
{"learn":[184.2335474],"iteration":513,"passed_time":34.88415834,"remaining_time":32.98385399},
{"learn":[183.9691556],"iteration":514,"passed_time":34.92558844,"remaining_time":32.89108815},
{"learn":[183.779245],"iteration":515,"passed_time":34.99116557,"remaining_time":32.82117081},
{"learn":[182.5515199],"iteration":516,"passed_time":35.06211337,"remaining_time":32.75628774},
{"learn":[181.74791],"iteration":517,"passed_time":35.09735717,"remaining_time":32.6581586},
{"learn":[180.835982],"iteration":518,"passed_time":35.16680428,"remaining_time":32.59197083},
{"learn":[180.1893866],"iteration":519,"passed_time":35.21898521,"remaining_time":32.5098325},
{"learn":[179.2449098],"iteration":520,"passed_time":35.27974717,"remaining_time":32.43569845},
{"learn":[178.1705033],"iteration":521,"passed_time":35.35603894,"remaining_time":32.37583642},
{"learn":[177.8449788],"iteration":522,"passed_time":35.40889362,"remaining_time":32.29453587},
{"learn":[176.8837554],"iteration":523,"passed_time":35.47977387,"remaining_time":32.22971825},
{"learn":[175.850727],"iteration":524,"passed_time":35.56227499,"remaining_time":32.17539166},
{"learn":[175.3545803],"iteration":525,"passed_time":35.6385705,"remaining_time":32.11536582},
{"learn":[174.3993546],"iteration":526,"passed_time":35.69309188,"remaining_time":32.03573522},
{"learn":[173.7167589],"iteration":527,"passed_time":35.7422557,"remaining_time":31.9514104},
{"learn":[172.7770463],"iteration":528,"passed_time":35.80743138,"remaining_time":31.88147482},
{"learn":[171.6590618],"iteration":529,"passed_time":35.85224045,"remaining_time":31.79349625},
{"learn":[170.6950096],"iteration":530,"passed_time":35.90523168,"remaining_time":31.71290708},
{"learn":[170.1980929],"iteration":531,"passed_time":35.943633,"remaining_time":31.61958692},
{"learn":[169.243638],"iteration":532,"passed_time":36.01096732,"remaining_time":31.55182315},
{"learn":[168.3222531],"iteration":533,"passed_time":36.05449144,"remaining_time":31.4632828},
{"learn":[167.8457081],"iteration":534,"passed_time":36.1207907,"remaining_time":31.39470593},
{"learn":[166.7857247],"iteration":535,"passed_time":36.17304859,"remaining_time":31.31398236},
{"learn":[165.9200679],"iteration":536,"passed_time":36.26006579,"remaining_time":31.26333419},
{"learn":[165.2236969],"iteration":537,"passed_time":36.33732259,"remaining_time":31.20416921},
{"learn":[164.4054142],"iteration":538,"passed_time":36.43765393,"remaining_time":31.16467247},
{"learn":[163.5900937],"iteration":539,"passed_time":36.51721574,"remaining_time":31.10725785},
{"learn":[162.7600742],"iteration":540,"passed_time":36.58202387,"remaining_time":31.03724391},
{"learn":[162.3147092],"iteration":541,"passed_time":36.65969058,"remaining_time":30.97811492},
{"learn":[161.4375559],"iteration":542,"passed_time":36.71120051,"remaining_time":30.89690356},
{"learn":[161.1152632],"iteration":543,"passed_time":36.76526998,"remaining_time":30.8179469},
{"learn":[160.4824775],"iteration":544,"passed_time":36.85724896,"remaining_time":30.77073079},
{"learn":[159.4747899],"iteration":545,"passed_time":36.94356338,"remaining_time":30.71864061},
{"learn":[158.5754221],"iteration":546,"passed_time":37.04392081,"remaining_time":30.67805507},
{"learn":[157.6396924],"iteration":547,"passed_time":37.11723577,"remaining_time":30.61494629},
{"learn":[157.2264468],"iteration":548,"passed_time":37.17904504,"remaining_time":30.54234848},
{"learn":[155.9486893],"iteration":549,"passed_time":37.24523776,"remaining_time":30.47337635},
{"learn":[155.2657139],"iteration":550,"passed_time":37.29231887,"remaining_time":30.38884061},
{"learn":[155.0280162],"iteration":551,"passed_time":37.34104006,"remaining_time":30.30577164},
{"learn":[154.2236147],"iteration":552,"passed_time":37.38062838,"remaining_time":30.21544464},
{"learn":[153.2406054],"iteration":553,"passed_time":37.46422358,"remaining_time":30.16072873},
{"learn":[152.5016164],"iteration":554,"passed_time":37.51601594,"remaining_time":30.08040918},
{"learn":[152.1941811],"iteration":555,"passed_time":37.60021266,"remaining_time":30.0260691},
{"learn":[151.2673856],"iteration":556,"passed_time":37.67190493,"remaining_time":29.96167663},
{"learn":[151.0744056],"iteration":557,"passed_time":37.7512285,"remaining_time":29.90330286},
{"learn":[150.2883882],"iteration":558,"passed_time":37.83416775,"remaining_time":29.84770658},
{"learn":[149.4589543],"iteration":559,"passed_time":37.91439524,"remaining_time":29.78988197},
{"learn":[148.8723925],"iteration":560,"passed_time":38.00779094,"remaining_time":29.74228204},
{"learn":[148.2689124],"iteration":561,"passed_time":38.04669129,"remaining_time":29.65204766},
{"learn":[147.5861316],"iteration":562,"passed_time":38.11021998,"remaining_time":29.58111213},
{"learn":[146.6214312],"iteration":563,"passed_time":38.15319956,"remaining_time":29.49431739},
{"learn":[145.8470857],"iteration":564,"passed_time":38.21694727,"remaining_time":29.42366737},
{"learn":[144.8887998],"iteration":565,"passed_time":38.26711982,"remaining_time":29.34263251},
{"learn":[143.9122883],"iteration":566,"passed_time":38.37686408,"remaining_time":29.30719955},
{"learn":[142.8540685],"iteration":567,"passed_time":38.46074447,"remaining_time":29.25183382},
{"learn":[141.9545127],"iteration":568,"passed_time":38.50356388,"remaining_time":29.16526543},
{"learn":[141.5192343],"iteration":569,"passed_time":38.60542717,"remaining_time":29.12339243},
{"learn":[140.7521105],"iteration":570,"passed_time":38.66812138,"remaining_time":29.05188104},
{"learn":[140.0845318],"iteration":571,"passed_time":38.72330005,"remaining_time":28.97477696},
{"learn":[139.678381],"iteration":572,"passed_time":38.76133124,"remaining_time":28.8849711},
{"learn":[139.3646679],"iteration":573,"passed_time":38.83904043,"remaining_time":28.82479307},
{"learn":[138.7673136],"iteration":574,"passed_time":38.91141699,"remaining_time":28.76061256},
{"learn":[138.0800605],"iteration":575,"passed_time":38.98978192,"remaining_time":28.70081169},
{"learn":[137.3046479],"iteration":576,"passed_time":39.04708323,"remaining_time":28.62550469},
{"learn":[137.1495474],"iteration":577,"passed_time":39.15703526,"remaining_time":28.58870048},
{"learn":[136.4563233],"iteration":578,"passed_time":39.22313735,"remaining_time":28.51975963},
{"learn":[136.1855007],"iteration":579,"passed_time":39.2931974,"remaining_time":28.45369467},
{"learn":[135.9423147],"iteration":580,"passed_time":39.37704945,"remaining_time":28.39756234},
{"learn":[135.5039755],"iteration":581,"passed_time":39.42655066,"remaining_time":28.31666353},
{"learn":[134.7228805],"iteration":582,"passed_time":39.46702938,"remaining_time":28.22941895},
{"learn":[134.1184701],"iteration":583,"passed_time":39.50809033,"remaining_time":28.14274928},
{"learn":[133.7506166],"iteration":584,"passed_time":39.58342404,"remaining_time":28.08054868},
{"learn":[133.4701041],"iteration":585,"passed_time":39.63882106,"remaining_time":28.00421829},
{"learn":[132.6436118],"iteration":586,"passed_time":39.6860898,"remaining_time":27.92224035},
{"learn":[132.0143322],"iteration":587,"passed_time":39.7577528,"remaining_time":27.85747305},
{"learn":[131.1966632],"iteration":588,"passed_time":39.80083098,"remaining_time":27.77273605},
{"learn":[130.5721504],"iteration":589,"passed_time":39.86496701,"remaining_time":27.70277368},
{"learn":[129.8149718],"iteration":590,"passed_time":39.94203704,"remaining_time":27.64178198},
{"learn":[129.5914423],"iteration":591,"passed_time":40.01255339,"remaining_time":27.57621923},
{"learn":[129.4008132],"iteration":592,"passed_time":40.08359103,"remaining_time":27.51099755},
{"learn":[129.0558685],"iteration":593,"passed_time":40.14728289,"remaining_time":27.44073544},
{"learn":[128.0848014],"iteration":594,"passed_time":40.20267738,"remaining_time":27.36484763},
{"learn":[127.3672218],"iteration":595,"passed_time":40.26753899,"remaining_time":27.29544589},
{"learn":[126.7439687],"iteration":596,"passed_time":40.33015317,"remaining_time":27.22454226},
{"learn":[126.1100221],"iteration":597,"passed_time":40.38771042,"remaining_time":27.15026687},
{"learn":[125.3355486],"iteration":598,"passed_time":40.42823329,"remaining_time":27.06464366},
{"learn":[124.9200492],"iteration":599,"passed_time":40.47387616,"remaining_time":26.98258411},
{"learn":[124.7966602],"iteration":600,"passed_time":40.55730437,"remaining_time":26.92573119},
{"learn":[124.4056767],"iteration":601,"passed_time":40.58013866,"remaining_time":26.82872955},
{"learn":[124.0309518],"iteration":602,"passed_time":40.66276036,"remaining_time":26.77133642},
{"learn":[123.1088118],"iteration":603,"passed_time":40.7060127,"remaining_time":26.68804806},
{"learn":[122.9294362],"iteration":604,"passed_time":40.74629064,"remaining_time":26.60295009},
{"learn":[122.6727799],"iteration":605,"passed_time":40.81265488,"remaining_time":26.53496044},
{"learn":[121.9879256],"iteration":606,"passed_time":40.86844859,"remaining_time":26.46013228},
{"learn":[121.1204186],"iteration":607,"passed_time":40.92853469,"remaining_time":26.38813421},
{"learn":[120.4904763],"iteration":608,"passed_time":40.96380865,"remaining_time":26.30024496},
{"learn":[120.1667748],"iteration":609,"passed_time":41.02073751,"remaining_time":26.22637316},
{"learn":[119.8492529],"iteration":610,"passed_time":41.07457009,"remaining_time":26.15058554},
{"learn":[119.2356829],"iteration":611,"passed_time":41.12474556,"remaining_time":26.07255111},
{"learn":[118.6550511],"iteration":612,"passed_time":41.17452833,"remaining_time":25.99435965},
{"learn":[117.9569361],"iteration":613,"passed_time":41.1977427,"remaining_time":25.89955811},
{"learn":[117.717231],"iteration":614,"passed_time":41.28592417,"remaining_time":25.84565985},
{"learn":[117.1305133],"iteration":615,"passed_time":41.34097559,"remaining_time":25.77099777},
{"learn":[116.8579195],"iteration":616,"passed_time":41.39047959,"remaining_time":25.69295573},
{"learn":[116.3147322],"iteration":617,"passed_time":41.43108975,"remaining_time":25.60950855},
{"learn":[115.7814451],"iteration":618,"passed_time":41.50067087,"remaining_time":25.54403166},
{"learn":[115.4393892],"iteration":619,"passed_time":41.56046509,"remaining_time":25.47254312},
{"learn":[115.0449601],"iteration":620,"passed_time":41.62629749,"remaining_time":25.40477737},
{"learn":[114.5122686],"iteration":621,"passed_time":41.72110778,"remaining_time":25.3546282},
{"learn":[114.3500731],"iteration":622,"passed_time":41.78396508,"remaining_time":25.28499974},
{"learn":[113.6279158],"iteration":623,"passed_time":41.8600158,"remaining_time":25.22334285},
{"learn":[113.498906],"iteration":624,"passed_time":41.92413572,"remaining_time":25.15448143},
{"learn":[112.9129419],"iteration":625,"passed_time":41.99264855,"remaining_time":25.08825968},
{"learn":[112.3930127],"iteration":626,"passed_time":42.05681623,"remaining_time":25.0194457},
{"learn":[111.7123067],"iteration":627,"passed_time":42.13030385,"remaining_time":24.95616725},
{"learn":[111.3070458],"iteration":628,"passed_time":42.20097065,"remaining_time":24.89119254},
{"learn":[110.7873341],"iteration":629,"passed_time":42.23231552,"remaining_time":24.80310594},
{"learn":[110.3039686],"iteration":630,"passed_time":42.27736879,"remaining_time":24.72321566},
{"learn":[109.7415802],"iteration":631,"passed_time":42.32302434,"remaining_time":24.64378632},
{"learn":[109.3515737],"iteration":632,"passed_time":42.38456908,"remaining_time":24.57367591},
{"learn":[108.9898508],"iteration":633,"passed_time":42.43332898,"remaining_time":24.496212},
{"learn":[108.5664704],"iteration":634,"passed_time":42.50531901,"remaining_time":24.43219124},
{"learn":[107.7709014],"iteration":635,"passed_time":42.57653496,"remaining_time":24.3677024},
{"learn":[107.5949202],"iteration":636,"passed_time":42.64155066,"remaining_time":24.29965917},
{"learn":[107.0497686],"iteration":637,"passed_time":42.70456546,"remaining_time":24.23049012},
{"learn":[106.4938226],"iteration":638,"passed_time":42.73893465,"remaining_time":24.14515713},
{"learn":[106.0060466],"iteration":639,"passed_time":42.78874808,"remaining_time":24.0686708},
{"learn":[105.5876181],"iteration":640,"passed_time":42.87001438,"remaining_time":24.00988325},
{"learn":[105.1653985],"iteration":641,"passed_time":42.94040364,"remaining_time":23.94496028},
{"learn":[104.9142877],"iteration":642,"passed_time":42.9918872,"remaining_time":23.86952368},
{"learn":[104.4419619],"iteration":643,"passed_time":43.08225373,"remaining_time":23.81565579},
{"learn":[103.9675932],"iteration":644,"passed_time":43.16704098,"remaining_time":23.75860395},
{"learn":[103.8036365],"iteration":645,"passed_time":43.23859871,"remaining_time":23.69421663},
{"learn":[103.3203603],"iteration":646,"passed_time":43.29505165,"remaining_time":23.62156604},
{"learn":[102.9417297],"iteration":647,"passed_time":43.34168915,"remaining_time":23.54363361},
{"learn":[102.3526339],"iteration":648,"passed_time":43.41467249,"remaining_time":23.48004629},
{"learn":[101.7123813],"iteration":649,"passed_time":43.48592452,"remaining_time":23.41549782},
{"learn":[100.9566649],"iteration":650,"passed_time":43.55926845,"remaining_time":23.35205021},
{"learn":[100.4556281],"iteration":651,"passed_time":43.63962529,"remaining_time":23.29231534},
{"learn":[99.94273778],"iteration":652,"passed_time":43.70688248,"remaining_time":23.22555624},
{"learn":[99.59802779],"iteration":653,"passed_time":43.76424713,"remaining_time":23.15356194},
{"learn":[99.16418741],"iteration":654,"passed_time":43.81703904,"remaining_time":23.07920377},
{"learn":[98.69785766],"iteration":655,"passed_time":43.88265168,"remaining_time":23.01163442},
{"learn":[97.99859282],"iteration":656,"passed_time":43.97470612,"remaining_time":22.95787549},
{"learn":[97.32226784],"iteration":657,"passed_time":44.02603956,"remaining_time":22.88283515},
{"learn":[96.95960609],"iteration":658,"passed_time":44.08351845,"remaining_time":22.81104673},
{"learn":[96.60666965],"iteration":659,"passed_time":44.14719781,"remaining_time":22.74249584},
{"learn":[96.27896216],"iteration":660,"passed_time":44.19521528,"remaining_time":22.66592735},
{"learn":[96.12854058],"iteration":661,"passed_time":44.25221449,"remaining_time":22.59403096},
{"learn":[95.59678317],"iteration":662,"passed_time":44.30430961,"remaining_time":22.51968678},
{"learn":[95.0204821],"iteration":663,"passed_time":44.36115466,"remaining_time":22.4478132},
{"learn":[94.52742951],"iteration":664,"passed_time":44.41955422,"remaining_time":22.37676791},
{"learn":[94.22500955],"iteration":665,"passed_time":44.48557645,"remaining_time":22.30958339},
{"learn":[93.73252908],"iteration":666,"passed_time":44.52126192,"remaining_time":22.2272567},
{"learn":[93.48323913],"iteration":667,"passed_time":44.58505758,"remaining_time":22.15904059},
{"learn":[92.95218919],"iteration":668,"passed_time":44.6236038,"remaining_time":22.07834508},
{"learn":[92.57677561],"iteration":669,"passed_time":44.68323614,"remaining_time":22.00816108},
{"learn":[92.04261429],"iteration":670,"passed_time":44.73646025,"remaining_time":21.9348665},
{"learn":[91.6014475],"iteration":671,"passed_time":44.80911374,"remaining_time":21.87111504},
{"learn":[91.04481386],"iteration":672,"passed_time":44.87573896,"remaining_time":21.80440808},
{"learn":[90.66671292],"iteration":673,"passed_time":44.8887445,"remaining_time":21.71176663},
{"learn":[90.33252206],"iteration":674,"passed_time":44.97308436,"remaining_time":21.65370729},
{"learn":[90.01046609],"iteration":675,"passed_time":45.02772524,"remaining_time":21.58133577},
{"learn":[89.51735711],"iteration":676,"passed_time":45.08308932,"remaining_time":21.50936167},
{"learn":[88.97727208],"iteration":677,"passed_time":45.17670258,"remaining_time":21.45560211},
{"learn":[88.90603055],"iteration":678,"passed_time":45.21833925,"remaining_time":21.37715302},
{"learn":[88.41262474],"iteration":679,"passed_time":45.27606194,"remaining_time":21.30638209},
{"learn":[88.02488614],"iteration":680,"passed_time":45.3457889,"remaining_time":21.24127263},
{"learn":[87.73654761],"iteration":681,"passed_time":45.40341225,"remaining_time":21.17050601},
{"learn":[87.28305552],"iteration":682,"passed_time":45.48597485,"remaining_time":21.1113529},
{"learn":[86.89532952],"iteration":683,"passed_time":45.55451968,"remaining_time":21.04565529},
{"learn":[86.43848787],"iteration":684,"passed_time":45.59097295,"remaining_time":20.96519194},
{"learn":[86.03243802],"iteration":685,"passed_time":45.63277865,"remaining_time":20.88730685},
{"learn":[85.59895894],"iteration":686,"passed_time":45.70950612,"remaining_time":20.82543729},
{"learn":[85.17819671],"iteration":687,"passed_time":45.78719968,"remaining_time":20.76396264},
{"learn":[84.82964297],"iteration":688,"passed_time":45.85611557,"remaining_time":20.69847887},
{"learn":[84.71238421],"iteration":689,"passed_time":45.92187008,"remaining_time":20.63156482},
{"learn":[84.3325361],"iteration":690,"passed_time":45.99610664,"remaining_time":20.56844711},
{"learn":[84.10677497],"iteration":691,"passed_time":46.07512259,"remaining_time":20.50742451},
{"learn":[83.91041123],"iteration":692,"passed_time":46.13245909,"remaining_time":20.43674595},
{"learn":[83.6643516],"iteration":693,"passed_time":46.18331807,"remaining_time":20.36324975},
{"learn":[83.19240477],"iteration":694,"passed_time":46.22392314,"remaining_time":20.28531879},
{"learn":[82.69761316],"iteration":695,"passed_time":46.31298516,"remaining_time":20.22866018},
{"learn":[82.31074705],"iteration":696,"passed_time":46.35204019,"remaining_time":20.15016955},
{"learn":[82.09901181],"iteration":697,"passed_time":46.40274336,"remaining_time":20.07683166},
{"learn":[81.59714013],"iteration":698,"passed_time":46.47372852,"remaining_time":20.01229225},
{"learn":[81.29761808],"iteration":699,"passed_time":46.54845411,"remaining_time":19.94933748},
{"learn":[80.91868682],"iteration":700,"passed_time":46.61250336,"remaining_time":19.8817953},
{"learn":[80.52768683],"iteration":701,"passed_time":46.67128094,"remaining_time":19.81202524},
{"learn":[80.10045258],"iteration":702,"passed_time":46.70269,"remaining_time":19.73072394},
{"learn":[79.82610438],"iteration":703,"passed_time":46.74299475,"remaining_time":19.65330461},
{"learn":[79.45200612],"iteration":704,"passed_time":46.80771733,"remaining_time":19.58620796},
{"learn":[78.96124834],"iteration":705,"passed_time":46.83391768,"remaining_time":19.5030762},
{"learn":[78.71901514],"iteration":706,"passed_time":46.91495955,"remaining_time":19.44283331},
{"learn":[78.33830213],"iteration":707,"passed_time":47.01589036,"remaining_time":19.39073444},
{"learn":[77.88401548],"iteration":708,"passed_time":47.09025349,"remaining_time":19.32759346},
{"learn":[77.71893701],"iteration":709,"passed_time":47.1847758,"remaining_time":19.2726549},
{"learn":[77.34298737],"iteration":710,"passed_time":47.26596544,"remaining_time":19.21218567},
{"learn":[77.01930648],"iteration":711,"passed_time":47.31320852,"remaining_time":19.13792704},
{"learn":[76.73253147],"iteration":712,"passed_time":47.37745629,"remaining_time":19.070589},
{"learn":[76.30777853],"iteration":713,"passed_time":47.43002267,"remaining_time":18.99858051},
{"learn":[75.95178784],"iteration":714,"passed_time":47.50648625,"remaining_time":18.93615186},
{"learn":[75.64899112],"iteration":715,"passed_time":47.55214806,"remaining_time":18.86146655},
{"learn":[75.4942802],"iteration":716,"passed_time":47.6141763,"remaining_time":18.79332203},
{"learn":[75.10108979],"iteration":717,"passed_time":47.67325148,"remaining_time":18.7240347},
{"learn":[74.9260902],"iteration":718,"passed_time":47.75046876,"remaining_time":18.6618661},
{"learn":[74.59523331],"iteration":719,"passed_time":47.81095683,"remaining_time":18.59314988},
{"learn":[74.19224402],"iteration":720,"passed_time":47.87805568,"remaining_time":18.52701461},
{"learn":[73.81427243],"iteration":721,"passed_time":47.94530175,"remaining_time":18.46093336},
{"learn":[73.62632016],"iteration":722,"passed_time":48.01043704,"remaining_time":18.3940402},
{"learn":[73.30303856],"iteration":723,"passed_time":48.08680219,"remaining_time":18.33143288},
{"learn":[73.01456011],"iteration":724,"passed_time":48.17124115,"remaining_time":18.27185009},
{"learn":[72.66887894],"iteration":725,"passed_time":48.24353261,"remaining_time":18.20761424},
{"learn":[72.54295731],"iteration":726,"passed_time":48.34372388,"remaining_time":18.15383304},
{"learn":[72.22614803],"iteration":727,"passed_time":48.41115234,"remaining_time":18.08768329},
{"learn":[72.06304561],"iteration":728,"passed_time":48.48010438,"remaining_time":18.02209641},
{"learn":[71.87503619],"iteration":729,"passed_time":48.54469441,"remaining_time":17.95488697},
{"learn":[71.80733858],"iteration":730,"passed_time":48.60177096,"remaining_time":17.88491982},
{"learn":[71.53421438],"iteration":731,"passed_time":48.6508484,"remaining_time":17.81205925},
{"learn":[71.23652545],"iteration":732,"passed_time":48.74432759,"remaining_time":17.7554372},
{"learn":[71.03154869],"iteration":733,"passed_time":48.80920165,"remaining_time":17.68834828},
{"learn":[70.76022098],"iteration":734,"passed_time":48.87702324,"remaining_time":17.62232811},
{"learn":[70.60057249],"iteration":735,"passed_time":48.92588627,"remaining_time":17.54950268},
{"learn":[70.47377407],"iteration":736,"passed_time":48.99629339,"remaining_time":17.48443034},
{"learn":[70.07052517],"iteration":737,"passed_time":49.05041813,"remaining_time":17.41356308},
{"learn":[69.87808658],"iteration":738,"passed_time":49.09184721,"remaining_time":17.33825727},
{"learn":[69.7259254],"iteration":739,"passed_time":49.12016725,"remaining_time":17.25843714},
{"learn":[69.31085834],"iteration":740,"passed_time":49.23420399,"remaining_time":17.20871637},
{"learn":[68.92647914],"iteration":741,"passed_time":49.30372603,"remaining_time":17.14334409},
{"learn":[68.74293976],"iteration":742,"passed_time":49.33566117,"remaining_time":17.06495952},
{"learn":[68.43332705],"iteration":743,"passed_time":49.38026048,"remaining_time":16.99105737},
{"learn":[68.06375268],"iteration":744,"passed_time":49.43048874,"remaining_time":16.91916057},
{"learn":[67.78259793],"iteration":745,"passed_time":49.48977414,"remaining_time":16.85040567},
{"learn":[67.3482988],"iteration":746,"passed_time":49.59239199,"remaining_time":16.79635231},
{"learn":[67.23443568],"iteration":747,"passed_time":49.65685402,"remaining_time":16.72931446},
{"learn":[67.10609208],"iteration":748,"passed_time":49.72726321,"remaining_time":16.66427646},
{"learn":[66.94721914],"iteration":749,"passed_time":49.78958766,"remaining_time":16.59652922},
{"learn":[66.62667764],"iteration":750,"passed_time":49.86621084,"remaining_time":16.53353728},
{"learn":[66.26708447],"iteration":751,"passed_time":49.88896553,"remaining_time":16.45274395},
{"learn":[65.86301319],"iteration":752,"passed_time":49.95174585,"remaining_time":16.38523403},
{"learn":[65.52376248],"iteration":753,"passed_time":50.011904,"remaining_time":16.31688115},
{"learn":[65.3226166],"iteration":754,"passed_time":50.06275466,"remaining_time":16.24552966},
{"learn":[65.16180909],"iteration":755,"passed_time":50.10497613,"remaining_time":16.17144732},
{"learn":[65.04791681],"iteration":756,"passed_time":50.16481081,"remaining_time":16.10310307},
{"learn":[64.85271586],"iteration":757,"passed_time":50.22580558,"remaining_time":16.03515165},
{"learn":[64.7230538],"iteration":758,"passed_time":50.2912939,"remaining_time":15.96864536},
{"learn":[64.55812234],"iteration":759,"passed_time":50.34667177,"remaining_time":15.89894898},
{"learn":[64.31470443],"iteration":760,"passed_time":50.4082343,"remaining_time":15.83123259},
{"learn":[64.15101306],"iteration":761,"passed_time":50.46131351,"remaining_time":15.7608827},
{"learn":[63.95296442],"iteration":762,"passed_time":50.52438055,"remaining_time":15.69368046},
{"learn":[63.5806137],"iteration":763,"passed_time":50.60842786,"remaining_time":15.63296986},
{"learn":[63.21396547],"iteration":764,"passed_time":50.68538865,"remaining_time":15.57002135},
{"learn":[62.86700407],"iteration":765,"passed_time":50.74461386,"remaining_time":15.50161833},
{"learn":[62.48649947],"iteration":766,"passed_time":50.81860316,"remaining_time":15.4377243},
{"learn":[62.06420137],"iteration":767,"passed_time":50.84522289,"remaining_time":15.35949441},
{"learn":[61.92060632],"iteration":768,"passed_time":50.91022966,"remaining_time":15.29292984},
{"learn":[61.63142866],"iteration":769,"passed_time":50.96057919,"remaining_time":15.22199119},
{"learn":[61.42961326],"iteration":770,"passed_time":51.02717258,"remaining_time":15.15593064},
{"learn":[61.12692112],"iteration":771,"passed_time":51.12735661,"remaining_time":15.09978926},
{"learn":[60.91495621],"iteration":772,"passed_time":51.22296861,"remaining_time":15.0421913},
{"learn":[60.53083885],"iteration":773,"passed_time":51.27380089,"remaining_time":14.9714199},
{"learn":[60.42388399],"iteration":774,"passed_time":51.33430049,"remaining_time":14.90350659},
{"learn":[60.1620655],"iteration":775,"passed_time":51.40645186,"remaining_time":14.8389758},
{"learn":[59.91719272],"iteration":776,"passed_time":51.49397385,"remaining_time":14.77883677},
{"learn":[59.6355481],"iteration":777,"passed_time":51.56484386,"remaining_time":14.71387575},
{"learn":[59.53183636],"iteration":778,"passed_time":51.62756993,"remaining_time":14.64658916},
{"learn":[59.30595421],"iteration":779,"passed_time":51.68591279,"remaining_time":14.57807797},
{"learn":[58.89736692],"iteration":780,"passed_time":51.75047003,"remaining_time":14.51133539},
{"learn":[58.61698551],"iteration":781,"passed_time":51.83044566,"remaining_time":14.44889662},
{"learn":[58.5167695],"iteration":782,"passed_time":51.89520823,"remaining_time":14.38219692},
{"learn":[58.27819279],"iteration":783,"passed_time":51.96065759,"remaining_time":14.31569138},
{"learn":[58.07747175],"iteration":784,"passed_time":51.99730378,"remaining_time":14.24129976},
{"learn":[57.95211415],"iteration":785,"passed_time":52.06782475,"remaining_time":14.17622709},
{"learn":[57.53805323],"iteration":786,"passed_time":52.13137697,"remaining_time":14.1092545},
{"learn":[57.19618855],"iteration":787,"passed_time":52.17533213,"remaining_time":14.03701829},
{"learn":[56.97905666],"iteration":788,"passed_time":52.22658825,"remaining_time":13.96680624},
{"learn":[56.83393614],"iteration":789,"passed_time":52.27603924,"remaining_time":13.89616233},
{"learn":[56.73037216],"iteration":790,"passed_time":52.34432695,"remaining_time":13.83054909},
{"learn":[56.64386808],"iteration":791,"passed_time":52.41641987,"remaining_time":13.76592845},
{"learn":[56.384664],"iteration":792,"passed_time":52.48494407,"remaining_time":13.7003574},
{"learn":[56.23856156],"iteration":793,"passed_time":52.54644969,"remaining_time":13.63295798},
{"learn":[56.11520256],"iteration":794,"passed_time":52.60696025,"remaining_time":13.56531679},
{"learn":[56.00130361],"iteration":795,"passed_time":52.66939507,"remaining_time":13.49818668},
{"learn":[55.72411878],"iteration":796,"passed_time":52.71072953,"remaining_time":13.42569397},
{"learn":[55.63455159],"iteration":797,"passed_time":52.78638853,"remaining_time":13.36196802},
{"learn":[55.43702766],"iteration":798,"passed_time":52.86617006,"remaining_time":13.29924929},
{"learn":[55.36210599],"iteration":799,"passed_time":52.91860939,"remaining_time":13.22965235},
{"learn":[55.08490244],"iteration":800,"passed_time":52.96919968,"remaining_time":13.15963887},
{"learn":[54.91954376],"iteration":801,"passed_time":53.03359806,"remaining_time":13.09308281},
{"learn":[54.65570611],"iteration":802,"passed_time":53.11936192,"remaining_time":13.03177372},
{"learn":[54.60898314],"iteration":803,"passed_time":53.17374751,"remaining_time":12.96275437},
{"learn":[54.55202443],"iteration":804,"passed_time":53.2336104,"remaining_time":12.89509817},
{"learn":[54.23215748],"iteration":805,"passed_time":53.27949218,"remaining_time":12.82409613},
{"learn":[54.04161307],"iteration":806,"passed_time":53.32691588,"remaining_time":12.75352511},
{"learn":[53.7906452],"iteration":807,"passed_time":53.41503591,"remaining_time":12.6926818},
{"learn":[53.71320037],"iteration":808,"passed_time":53.46940012,"remaining_time":12.62380151},
{"learn":[53.53791296],"iteration":809,"passed_time":53.50997529,"remaining_time":12.5517226},
{"learn":[53.35329197],"iteration":810,"passed_time":53.57769885,"remaining_time":12.48604819},
{"learn":[53.22883002],"iteration":811,"passed_time":53.63001252,"remaining_time":12.41680093},
{"learn":[53.14025185],"iteration":812,"passed_time":53.66775677,"remaining_time":12.34424418},
{"learn":[52.81850715],"iteration":813,"passed_time":53.75154369,"remaining_time":12.28229377},
{"learn":[52.53391393],"iteration":814,"passed_time":53.78905031,"remaining_time":12.20978443},
{"learn":[52.32864181],"iteration":815,"passed_time":53.84463044,"remaining_time":12.14143628},
{"learn":[52.25539424],"iteration":816,"passed_time":53.90814049,"remaining_time":12.07489561},
{"learn":[52.11925124],"iteration":817,"passed_time":53.98304914,"remaining_time":12.01089846},
{"learn":[51.83426458],"iteration":818,"passed_time":54.04382823,"remaining_time":11.94375203},
{"learn":[51.55927528],"iteration":819,"passed_time":54.10339076,"remaining_time":11.87635407},
{"learn":[51.48825415],"iteration":820,"passed_time":54.1678057,"remaining_time":11.81003316},
{"learn":[51.42288387],"iteration":821,"passed_time":54.23127163,"remaining_time":11.74351137},
{"learn":[51.11280486],"iteration":822,"passed_time":54.30583844,"remaining_time":11.67938445},
{"learn":[50.92602629],"iteration":823,"passed_time":54.35578018,"remaining_time":11.60997247},
{"learn":[50.74526323],"iteration":824,"passed_time":54.43313244,"remaining_time":11.54642203},
{"learn":[50.54556928],"iteration":825,"passed_time":54.48300208,"remaining_time":11.47704886},
{"learn":[50.33866185],"iteration":826,"passed_time":54.5402103,"remaining_time":11.40925802},
{"learn":[49.98164424],"iteration":827,"passed_time":54.62193413,"remaining_time":11.34658535},
{"learn":[49.90347751],"iteration":828,"passed_time":54.68161277,"remaining_time":11.2793194},
{"learn":[49.83914929],"iteration":829,"passed_time":54.77270399,"remaining_time":11.21850564},
{"learn":[49.58244063],"iteration":830,"passed_time":54.8054693,"remaining_time":11.1457573},
{"learn":[49.37021066],"iteration":831,"passed_time":54.84433315,"remaining_time":11.0743365},
{"learn":[49.10497364],"iteration":832,"passed_time":54.9065707,"remaining_time":11.00767984},
{"learn":[48.92848349],"iteration":833,"passed_time":54.95533104,"remaining_time":10.93835126},
{"learn":[48.82312746],"iteration":834,"passed_time":55.02441717,"remaining_time":10.87308842},
{"learn":[48.67102941],"iteration":835,"passed_time":55.06049242,"remaining_time":10.80134062},
{"learn":[48.42007352],"iteration":836,"passed_time":55.13721889,"remaining_time":10.7375946},
{"learn":[48.19119939],"iteration":837,"passed_time":55.18241369,"remaining_time":10.66772198},
{"learn":[47.91067834],"iteration":838,"passed_time":55.24195026,"remaining_time":10.6006603},
{"learn":[47.80159346],"iteration":839,"passed_time":55.29195546,"remaining_time":10.53180104},
{"learn":[47.56188631],"iteration":840,"passed_time":55.33851778,"remaining_time":10.4623357},
{"learn":[47.38706017],"iteration":841,"passed_time":55.38003584,"remaining_time":10.39197822},
{"learn":[47.12899719],"iteration":842,"passed_time":55.44663903,"remaining_time":10.32636101},
{"learn":[47.04384725],"iteration":843,"passed_time":55.53231734,"remaining_time":10.26426719},
{"learn":[46.84357925],"iteration":844,"passed_time":55.60120445,"remaining_time":10.1990375},
{"learn":[46.62716384],"iteration":845,"passed_time":55.65402254,"remaining_time":10.13087408},
{"learn":[46.55096126],"iteration":846,"passed_time":55.69980177,"remaining_time":10.06147541},
{"learn":[46.49481654],"iteration":847,"passed_time":55.76122555,"remaining_time":9.994936655},
{"learn":[46.4361027],"iteration":848,"passed_time":55.83113332,"remaining_time":9.929918883},
{"learn":[46.23359944],"iteration":849,"passed_time":55.88783953,"remaining_time":9.862559917},
{"learn":[46.11679244],"iteration":850,"passed_time":55.95310996,"remaining_time":9.79672548},
{"learn":[45.89463239],"iteration":851,"passed_time":56.00968054,"remaining_time":9.729381127},
{"learn":[45.68219631],"iteration":852,"passed_time":56.08766052,"remaining_time":9.665751579},
{"learn":[45.43618584],"iteration":853,"passed_time":56.17880608,"remaining_time":9.604339213},
{"learn":[45.19108647],"iteration":854,"passed_time":56.23462395,"remaining_time":9.536866051},
{"learn":[45.11564918],"iteration":855,"passed_time":56.30367442,"remaining_time":9.471646164},
{"learn":[44.90070993],"iteration":856,"passed_time":56.35668324,"remaining_time":9.40374061},
{"learn":[44.84247971],"iteration":857,"passed_time":56.40977056,"remaining_time":9.335882774},
{"learn":[44.71828195],"iteration":858,"passed_time":56.45992972,"remaining_time":9.267578684},
{"learn":[44.67070286],"iteration":859,"passed_time":56.52230553,"remaining_time":9.201305552},
{"learn":[44.54121476],"iteration":860,"passed_time":56.60203744,"remaining_time":9.137843443},
{"learn":[44.24143795],"iteration":861,"passed_time":56.67446975,"remaining_time":9.073174972},
{"learn":[44.20298321],"iteration":862,"passed_time":56.73412957,"remaining_time":9.006460893},
{"learn":[44.1606444],"iteration":863,"passed_time":56.79060251,"remaining_time":8.939261505},
{"learn":[43.89735253],"iteration":864,"passed_time":56.85283288,"remaining_time":8.872985478},
{"learn":[43.7103552],"iteration":865,"passed_time":56.91664721,"remaining_time":8.806963887},
{"learn":[43.66615164],"iteration":866,"passed_time":56.9577595,"remaining_time":8.737464837},
{"learn":[43.46220861],"iteration":867,"passed_time":57.01713969,"remaining_time":8.670809261},
{"learn":[43.34111866],"iteration":868,"passed_time":57.09464786,"remaining_time":8.606903187},
{"learn":[43.17625456],"iteration":869,"passed_time":57.17758833,"remaining_time":8.543777567},
{"learn":[43.11634667],"iteration":870,"passed_time":57.22192162,"remaining_time":8.474888506},
{"learn":[42.82822845],"iteration":871,"passed_time":57.26484346,"remaining_time":8.405848582},
{"learn":[42.78930565],"iteration":872,"passed_time":57.30359333,"remaining_time":8.336261572},
{"learn":[42.5721601],"iteration":873,"passed_time":57.3381465,"remaining_time":8.266140114},
{"learn":[42.50796903],"iteration":874,"passed_time":57.387495,
{"learn":[53.1659165],"iterati,
{"learn":[42.26573301],"iteration":875,"passed_time":57.4445,
{"learn":[52.90571659],"iteratio,
{"learn":[42.20261651],"iteration":876,"passed_time":57.5049,
{"learn":[52.80806709],"iteration":877,"passed_time":57.48049991,"remaining_time":7.987039851},
{"learn":[52.75248699],"iteratio,
{"learn":[41.81457667],"iteration":878,"passed_time":57.6042,
{"learn":[52.48745199],"iteratio,
{"learn":[41.59009074],"iteration":879,"passed_time":57.68215571,"remaining_time":7.865748507},
{"learn":[41.5124515],"iteration":880,"passed_time":57.74448,
{"learn":[52.1243423],"iteratio,
{"learn":[41.38739069],"iteration":881,"passed_time":57.8169,
{"learn":[51.98282805],"iteratio,
{"learn":[41.31118053],"iteration":882,"passed_time":57.88304356,"remaining_time":7.669667153},
{"learn":[41.18251956],"iteration":883,"passed_time":57.9159,
{"learn":[51.59442416],"iteration":884,"passed_time":57.91791013,"remaining_time":7.526056119},
{"learn":[51.4731957],"iteration":885,"passed_time":57.97104838,"remaining_time":7.459028799},
{"learn":[51.34230652],"iteration,
{"learn":[40.79719609],"iteration":886,"passed_time":58.108,
{"learn":[51.08537871],"iterati,
{"learn":[40.6288996],"iteration":887,"passed_time":58.174064,
{"learn":[50.82472147],"iterat,
{"learn":[40.42845162],"iteration":888,"passed_time":58.2743029,"remaining_time":7.276094063},
{"learn":[40.34407463],"iteration":889,"passed_time":58.32512125,"remaining_time":7.208722851},
{"learn":[40.20127163],"iteration":890,"passed_time":58.39495531,"remaining_time":7.143715071},
{"learn":[40.01798578],"iteration":891,"passed_time":58.443379,
{"learn":[50.29884508],"iterat,
{"learn":[39.80146825],"iteration":892,"passed_time":58.488717,
{"learn":[50.03350752],"iterat,
{"learn":[39.57641329],"iteration":893,"passed_time":58.584019,
{"learn":[49.96796308],"iterat,
{"learn":[39.48746665],"iteration":894,"passed_time":58.63511,
{"learn":[49.7881887],"iteratio,
{"learn":[39.28296331],"iteration":895,"passed_time":58.6974,
{"learn":[49.67127912],"iteratio,
{"learn":[39.11670758],"iteration":896,"passed_time":58.82015038,"remaining_time":6.754153276},
{"learn":[39.00595252],"iteration":897,"passed_time":58.89095391,"remaining_time":6.689172939},
{"learn":[38.74300784],"iteration":898,"passed_time":58.95135636,"remaining_time":6.623011115},
{"learn":[38.67726737],"iteration":899,"passed_time":59.0304714,"remaining_time":6.558941267},
{"learn":[38.62905851],"iteration":900,"passed_time":59.07349562,"remaining_time":6.490872438},
{"learn":[38.46058604],"iteration":901,"passed_time":59.13166635,"remaining_time":6.42450477},
{"learn":[38.34147083],"iteration":902,"passed_time":59.16495132,"remaining_time":6.355482035},
{"learn":[38.27184755],"iteration":903,"passed_time":59.23519609,"remaining_time":6.290463302},
{"learn":[38.22207913],"iteration":904,"passed_time":59.28849755,"remaining_time":6.223654439},
{"learn":[38.07780944],"iteration":905,"passed_time":59.34809906,"remaining_time":6.157529041},
{"learn":[38.01625979],"iteration":906,"passed_time":59.4,
{"learn":[48.22285566],"iteration":,
{"learn":[37.9373945],"iteration":907,"passed_time":59.46,
{"learn":[47.95573838],"iteration",
{"learn":[37.86839678],"iteration":908,"passed_time":59.50,
{"learn":[47.87680028],"iteration",
{"learn":[37.67434599],"iteration":909,"passed_time":59.55,
{"learn":[47.78732399],"iteration",
{"learn":[37.59234647],"iteration":910,"passed_time":59.61,
{"learn":[47.58196902],"iteration":911,"passed_time":59.62078299,"remaining_time":5.752882569},
{"learn":[47.5144819],"iteration",
{"learn":[37.26185355],"iteration":912,"passed_time":59.75,
{"learn":[47.32138434],"iteration",
{"learn":[37.08860333],"iteration":913,"passed_time":59.82,
{"learn":[47.12832678],"iteration",
{"learn":[36.92613275],"iteration":914,"passed_time":59.8,
{"learn":[46.85921263],"iteration",
{"learn":[36.76862176],"iteration":915,"passed_time":59.95,
{"learn":[46.79333968],"iteration",
{"learn":[36.53405369],"iteration":916,"passed_time":60.00,
{"learn":[46.49947328],"iteration",
{"learn":[36.46383146],"iteration":917,"passed_time":60.06,
{"learn":[46.35794106],"iteration":918,"passed_time":60.04606684,"remaining_time":5.292417208},
{"learn":[46.21318071],"iteration":919,"passed_time":60.10990869,"remaining_time":5.226948582},
{"learn":[45.88986972],"iteration":920,"passed_time":60.18797521,"remaining_time":5.162703629},
{"learn":[45.72150032],"iteration":921,"passed_time":60.25379271,"remaining_time":5.097392442},
{"learn":[45.45236856],"iteration":922,"passed_time":60.31409163,"remaining_time":5.031619778},
{"learn":[45.23407422],"iteration":923,"passed_time":60.35798363,"remaining_time":4.964509476},
{"learn":[45.03308486],"iteration":924,"passed_time":60.41049813,"remaining_time":4.898148497},
{"learn":[44.9811929],"iteration":925,"passed_time":60.50461559,"remaining_time":4.835142066},
{"learn":[44.84432101],"iteration":926,"passed_time":60.58494168,"remaining_time":4.770982462},
{"learn":[44.78566676],"iteration":927,"passed_time":60.6649306,"remaining_time":4.706761857},
{"learn":[44.59063661],"iteration":928,"passed_time":60.74269036,"remaining_time":4.642336938},
{"learn":[44.37693104],"iteration":929,"passed_time":60.8236965,"remaining_time":4.578127694},
{"learn":[44.25129802],"iteration":930,"passed_time":60.89529333,"remaining_time":4.513185005},
{"learn":[44.17255181],"iteration":931,"passed_time":60.94896515,"remaining_time":4.446920204},
{"learn":[44.12055303],"iteration":932,"passed_time":61.01503944,"remaining_time":4.381573036},
{"learn":[44.05152284],"iteration":933,"passed_time":61.07530093,"remaining_time":4.315813556},
{"learn":[43.77745758],"iteration":934,"passed_time":61.11532205,"remaining_time":4.248658752},
{"learn":[43.5525617],"iteration":935,"passed_time":61.15909333,"remaining_time":4.181818348},
{"learn":[43.34462006],"iteration":936,"passed_time":61.2256053,"remaining_time":4.116556173},
{"learn":[43.10786062],"iteration",
{"learn":[33.97394823],"iteration":937,"passed_time":61.3,
{"learn":[43.02106567],"iteration",
{"learn":[33.91745274],"iteration":938,"passed_time":61.4,
{"learn":[42.79388788],"iteration",
{"learn":[33.82262124],"iteration":939,"passed_time":61.47,
{"learn":[42.62313454],"iteration",
{"learn":[33.65319626],"iteration":940,"passed_time":61.5,
{"learn":[42.45039301],"iteration":,
{"learn":[33.46563247],"iteration":941,"passed_time":61.6,
{"learn":[42.36818463],"iteration":,
{"learn":[33.29310712],"iteration":942,"passed_time":61.67345911,"remaining_time":3.727876107},
{"learn":[33.23412336],"iteration":943,"passed_time":61.76426475,"remaining_time":3.663981807},
{"learn":[33.0592877],"iteration":944,"passed_time":61.85059577,"remaining_time":3.599770124},
{"learn":[32.92079395],"iteration":945,"passed_time":61.91214573,"remaining_time":3.534097113},
{"learn":[32.72785884],"iteration":946,"passed_time":61.9577877,"remaining_time":3.467542501},
{"learn":[32.56936507],"iteration":947,"passed_time":62.01162719,"remaining_time":3.40148166},
{"learn":[32.41447466],"iteration":948,"passed_time":62.07629172,"remaining_time":3.336028322},
{"learn":[32.31394191],"iteration":949,"passed_time":62.12023519,"remaining_time":3.269486063},
{"learn":[32.2754928],"iteration":950,"passed_time":62.18926244,"remaining_time":3.204283764},
{"learn":[32.24989299],"iteration":951,"passed_time":62.25504021,"remaining_time":3.138909591},
{"learn":[32.08771672],"iteration":952,"passed_time":62.31138093,"remaining_time":3.073069154},
{"learn":[31.95871287],"iteration":953,"passed_time":62.37614781,"remaining_time":3.007654926},
{"learn":[31.87489673],"iteration":954,"passed_time":62.43679572,"remaining_time":2.942047966},
{"learn":[31.79069745],"iteration":955,"passed_time":62.48333632,"remaining_time":2.87580209},
{"learn":[31.66920409],"iteration":956,"passed_time":62.54348267,"remaining_time":2.81020873},
{"learn":[31.51544438],"iteration":957,"passed_time":62.60451652,"remaining_time":2.744665651},
{"learn":[31.46466934],"iteration":958,"passed_time":62.65620995,"remaining_time":2.678732646},
{"learn":[31.3598841],"iteration":959,"passed_time":62.70488552,"remaining_time":2.612703563},
{"learn":[31.29207942],"iteration":960,"passed_time":62.77014459,"remaining_time":2.547383599},
{"learn":[31.11938599],"iteration":961,"passed_time":62.81216958,"remaining_time":2.481145992},
{"learn":[30.99673367],"iteration":962,"passed_time":62.84631683,"remaining_time":2.414655994},
{"learn":[30.84607535],"iteration":963,"passed_time":62.90349157,"remaining_time":2.349093046},
{"learn":[30.78374455],"iteration":964,"passed_time":62.96774636,"remaining_time":2.283804272},
{"learn":[30.69657077],"iteration":965,"passed_time":63.01269674,"remaining_time":2.217838188},
{"learn":[30.558484],"iteration":966,"passed_time":63.10435182,"remaining_time":2.153509421},
{"learn":[30.35667518],"iteration":967,"passed_time":63.15145839,"remaining_time":2.087651517},
{"learn":[30.21642756],"iteration":968,"passed_time":63.21808727,"remaining_time":2.022456868},
{"learn":[30.01930043],"iteration":969,"passed_time":63.24234857,"remaining_time":1.955948925},
{"learn":[29.82255972],"iteration":970,"passed_time":63.2985104,"remaining_time":1.890480743},
{"learn":[29.64900902],"iteration":971,"passed_time":63.34531086,"remaining_time":1.824762041},
{"learn":[29.59489764],"iteration":972,"passed_time":63.39105578,"remaining_time":1.759052935},
{"learn":[29.43564234],"iteration":973,"passed_time":63.42735933,"remaining_time":1.693132795},
{"learn":[29.31675043],"iteration":974,"passed_time":63.46662701,"remaining_time":1.627349411},
{"learn":[29.15305586],"iteration":975,"passed_time":63.49195165,"remaining_time":1.5612775},
{"learn":[29.07825541],"iteration":976,"passed_time":63.51569926,"remaining_time":1.495251876},
{"learn":[29.0046018],"iteration":977,"passed_time":63.55272075,"remaining_time":1.429611305},
{"learn":[28.84846106],"iteration":978,"passed_time":63.58186992,"remaining_time":1.363860335},
{"learn":[28.72409028],"iteration":979,"passed_time":63.60382554,"remaining_time":1.298037256},
{"learn":[28.55654568],"iteration":980,"passed_time":63.62534684,"remaining_time":1.232295199},
{"learn":[28.38797012],"iteration":981,"passed_time":63.64639962,"remaining_time":1.166634616},
{"learn":[28.30943705],"iteration":982,"passed_time":63.66392144,"remaining_time":1.101003728},
{"learn":[28.26436068],"iteration":983,"passed_time":63.68125589,"remaining_time":1.035467576},
{"learn":[28.20141617],"iteration":984,"passed_time":63.70421436,"remaining_time":0.9701149394},
{"learn":[28.07762828],"iteration":985,"passed_time":63.73299221,"remaining_time":0.9049309239},
{"learn":[28.02014039],"iteration":986,"passed_time":63.75994716,"remaining_time":0.8397966697},
{"learn":[27.94804072],"iteration":987,"passed_time":63.78017852,"remaining_time":0.7746580387},
{"learn":[27.77933105],"iteration":988,"passed_time":63.79269693,"remaining_time":0.709524435},
{"learn":[27.63892744],"iteration":989,"passed_time":63.80692889,"remaining_time":0.6445144333},
{"learn":[27.59153292],"iteration":990,"passed_time":63.82097747,"remaining_time":0.5796052444},
{"learn":[27.53888837],"iteration":991,"passed_time":63.83468944,"remaining_time":0.5147958825},
{"learn":[27.49103912],"iteration":992,"passed_time":63.84832359,"remaining_time":0.4500888873},
{"learn":[27.40968655],"iteration":993,"passed_time":63.86089912,"remaining_time":0.3854782643},
{"learn":[27.29195525],"iteration":994,"passed_time":63.87430328,"remaining_time":0.3209763984},
{"learn":[27.17995759],"iteration":995,"passed_time":63.88876292,"remaining_time":0.2565813772},
{"learn":[27.14215037],"iteration":996,"passed_time":63.90229952,"remaining_time":0.1922837498},
{"learn":[27.04514072],"iteration":997,"passed_time":63.91703548,"remaining_time":0.1280902515},
{"learn":[26.90050548],"iteration":998,"passed_time":63.92713741,"remaining_time":0.06399112854},
{"learn":[26.80098154],"iteration":999,"passed_time":63.93730697,"remaining_time":0}
]}}